prac5_atempt2/adc.v
// TSC simulation module

// set simulation time:
`timescale 1ns / 1ns

module ADC (
    input wire req,      // Request signal from TSC
    input wire rst,      // Reset signal for ADC
    output reg rdy,      // Ready signal to indicate completion
    output reg [7:0] dat // Data output from the array
);

// Constant array of values (16 data values)
  // reg [7:0]
  // integer adc_data [15:0] = {
  reg [0:7] adc_data [0:15];
    
  initial
    begin 
      // hard-coded ADC values stored in adc_data
      // it seams iVerilog doesn't want to initialize an array
      adc_data[ 0] = 8'h8B;
      adc_data[ 1] = 8'h8C;
      adc_data[ 2] = 8'h99;
      adc_data[ 3] = 8'h9B;
      adc_data[ 4] = 8'h93;
      adc_data[ 5] = 8'h82;
      adc_data[ 6] = 8'h97;
      adc_data[ 7] = 8'h90;
      adc_data[ 8] = 8'h9F;
      adc_data[ 9] = 8'hD7;
      adc_data[10] = 8'h8D;
      adc_data[11] = 8'h9C;
      adc_data[12] = 8'h85;
      adc_data[13] = 8'h8A;
      adc_data[14] = 8'h91;
      adc_data[15] = 8'h8C;
    end
  
  
  reg [7:0] idx = 0; // Index to access the array
  

always @(posedge req or posedge rst) begin
    if (rst) begin
        // Reset the device
        rdy <= 0;
        dat <= 8'b00000000; // Reset data output
        idx <= 0; // Reset array index
    end else if (req) begin
        // Read data from the sample array using modular arithmetic
        dat <= adc_data[idx % 16]; // Wrap around if idx exceeds 15
        idx <= idx + 1;

        // Raise RDY line
        rdy <= 1;
    end else begin
        // Lower RDY line if not processing
        rdy <= 0;
    end
end

endmodule

prac5_atempt2/TSC1.v
`timescale 1ns / 1ns
`include "adc.v"

module TSC1 (clk, reset, start, state_out, req_out, rst_out, rdy_out, dat_out, buffer_out_head, buffer_out_tail, TRIGTM);
  // Inputs
  input wire clk;        // Clock input
  input wire reset;      // Reset input
  input wire start;      // Start input



  // Outputs
  output reg req_out;    // Direction declaration for req_out
  output reg rst_out;    // Direction declaration for rst_out
  output reg rdy_out;    // Direction declaration for rdy_out
  output reg [7:0] dat_out;  // Direction declaration for dat_out
  output reg [7:0] buffer_out_head;  // Direction declaration for buffer_out0
  output reg [7:0] buffer_out_tail;  // Direction declaration for buffer_out1
  output reg [31:0] TRIGTM;  // Direction declaration for TRIGTM


  // Variables
  integer i = 0;
  integer head=15;
  integer tail= 0; 
  reg [7:0] buffer [0:31];  // Ring buffer with 10 elements
  reg [7:0] TRIGVl = 8'h9D;
  reg [31:0] timer = 32'h0000;

  // State machine
  `define STOP 2'b00     // Define STOP state as 2'b00
  `define READY 2'b01    // Define READY state as 2'b01
  `define RUNNING 2'b10  // Define RUNNING state as 2'b10
  `define triggered 2'b10  // Define RUNNING state as 2'b10

  // Signals
  reg req=0;
  reg rst=0;
  wire rdy;
  wire [7:0] dat;


  initial begin
    assign req_out = req;
    assign rst_out = rst;
    assign rdy_out = rdy;
    assign dat_out = dat;     
  end
  

  // Instantiate ADC module
  ADC adc_inst (
    .req(req),
    .rst(rst),
    .rdy(rdy),
    .dat(dat)
  );

  // Start the program 
  reg [1:0] state = `STOP;  // Register to hold the current state, initialized to STOP state
  output reg[1:0] state_out = 2'b00;  // Output register to display the current state, initialized to 2'b00

  always @(posedge reset) begin  // On positive edge of reset signal
    if ((state == `STOP) || (state == `RUNNING)) begin  // If the current state is STOP or RUNNING
      state = `READY;  // Change the state to READY
      rst = 1; // Resets the ADC
      // Reset the buffer
    end
  end

  always @(posedge start) begin  // On positive edge of start signal
    if (state == `READY) begin  // If the current state is READY
      state = `RUNNING;  // Change the state to RUNNING
      rst = 0; // Resets the ADC
    end
  end

  always @(posedge clk) begin  // On positive edge of clock signal
    timer++;  // Increment the timer
    
    state_out = state;  // Assign the current state to the output register
    if (state == `RUNNING) begin
      req = 1; // Request the ADC  
    end
  end

  always @(negedge clk) begin  // On negative edge of clock signal
    state_out = state;  // Assign the current state to the output register
    if (state == `RUNNING) begin
      req = 0; // Request the ADC 

      // Store the data in the ring buffer
      // output the buffers
      buffer_out_tail <= buffer[tail];
      buffer_out_head <= buffer[head];
      // Increment the head and tail pointers
      head = head + 1;
      tail = tail + 1;
      if (head == 32) begin
        head = 0;
      end
      if (tail == 32) begin
        tail = 0;
      end
      // Store the new data in the buffer
      buffer[tail] <= dat; 

      
      if (buffer_out_tail > TRIGVl) begin
        TRIGTM = timer;
        state = `triggered;
      end     
    end
  end

  
  
endmodule

prac5_atempt2/TSC1_tb.v

`timescale 1ns / 1ns
`include "TSC1.v"

module TSC1_tb;

  // Inputs
  reg clk; // Added clock signal
  reg reset;
  reg start;
  

  // Outputs
  output wire[1:0] state_out;
  output wire req_out;
  output wire rst_out;
  output wire rdy_out;
  output wire [7:0] dat_out;
  output wire [7:0] buffer_out_tail;
  output wire [7:0] buffer_out_head;
  output wire [31:0] TRIGTM;
  
 
 

  // Instantiate the Unit Under Test (UUT)
  TSC1 uut(
    clk, reset, start, state_out, req_out, rst_out, rdy_out, dat_out,
     buffer_out_tail, buffer_out_head , TRIGTM);

  initial begin
    // Initialize Inputs
    $dumpfile("TSC1_tb.vcd");
    $dumpvars(0, TSC1_tb); // Add hello_tb to waveform dump



    
    clk = 0;
    reset = 0;
    start = 0;

    #10

    reset = 1;

    #10

    reset = 0;

    #10 

    start = 1;

    #10

    start = 0;

    #500

    $display("test complete");
    $finish; // Added $finish to end the simulation
  end

  always begin
    #1 clk = ~clk; // Generate a clock signal with a period of 20ns
  end 

  always @(negedge clk) begin
    $display("buffer_out_tail: %h, buffer_out_head: %h, time %h", buffer_out_tail, buffer_out_head, TRIGTM); 
  end 
endmodule

prac5_atempt2/TSC1_tb.vcd
$date
	Sun Apr 28 17:13:57 2024
$end
$version
	Icarus Verilog
$end
$timescale
	1ns
$end
$scope module TSC1_tb $end
$var wire 2 ! state_out [1:0] $end
$var wire 1 " rst_out $end
$var wire 1 # req_out $end
$var wire 1 $ rdy_out $end
$var wire 8 % dat_out [7:0] $end
$var wire 8 & buffer_out_tail [7:0] $end
$var wire 8 ' buffer_out_head [7:0] $end
$var wire 32 ( TRIGTM [31:0] $end
$var reg 1 ) clk $end
$var reg 1 * reset $end
$var reg 1 + start $end
$scope module uut $end
$var wire 1 ) clk $end
$var wire 1 * reset $end
$var wire 1 + start $end
$var wire 1 , rdy $end
$var wire 8 - dat [7:0] $end
$var reg 32 . TRIGTM [31:0] $end
$var reg 8 / TRIGVl [7:0] $end
$var reg 8 0 buffer_out_head [7:0] $end
$var reg 8 1 buffer_out_tail [7:0] $end
$var reg 8 2 dat_out [7:0] $end
$var reg 1 $ rdy_out $end
$var reg 1 3 req $end
$var reg 1 # req_out $end
$var reg 1 4 rst $end
$var reg 1 " rst_out $end
$var reg 2 5 state [1:0] $end
$var reg 2 6 state_out [1:0] $end
$var reg 32 7 timer [31:0] $end
$var integer 32 8 head [31:0] $end
$var integer 32 9 i [31:0] $end
$var integer 32 : tail [31:0] $end
$scope module adc_inst $end
$var wire 1 3 req $end
$var wire 1 4 rst $end
$var reg 8 ; dat [7:0] $end
$var reg 8 < idx [7:0] $end
$var reg 1 , rdy $end
$upscope $end
$upscope $end
$upscope $end
$enddefinitions $end
$comment Show the parameter values. $end
$dumpall
$end
#0
$dumpvars
b0 <
bx ;
b0 :
b0 9
b1111 8
b0 7
b0 6
b0 5
04
03
bx 2
bx 1
bx 0
b10011101 /
bx .
bx -
x,
0+
0*
0)
bx (
bx '
bx &
bx %
x$
0#
0"
b0 !
$end
#1
b1 7
1)
#2
0)
#3
b10 7
1)
#4
0)
#5
b11 7
1)
#6
0)
#7
b100 7
1)
#8
0)
#9
b101 7
1)
#10
b0 %
b0 2
b0 -
b0 ;
0$
0,
b1 !
b1 6
1"
14
b1 5
0)
1*
#11
b110 7
1)
#12
0)
#13
b111 7
1)
#14
0)
#15
b1000 7
1)
#16
0)
#17
b1001 7
1)
#18
0)
#19
b1010 7
1)
#20
0)
0*
#21
b1011 7
1)
#22
0)
#23
b1100 7
1)
#24
0)
#25
b1101 7
1)
#26
0)
#27
b1110 7
1)
#28
0)
#29
b1111 7
1)
#30
b1 :
b10000 8
b10 !
b10 6
0"
04
b10 5
0)
1+
#31
1$
1,
b1 <
b10001011 %
b10001011 2
b10001011 -
b10001011 ;
1#
13
b10000 7
1)
#32
b0 '
b0 1
b10 :
b10001 8
0#
03
0)
#33
b10 <
b10001100 %
b10001100 2
b10001100 -
b10001100 ;
1#
13
b10001 7
1)
#34
b10001011 '
b10001011 1
b11 :
b10010 8
0#
03
0)
#35
b11 <
b10011001 %
b10011001 2
b10011001 -
b10011001 ;
1#
13
b10010 7
1)
#36
b10001100 '
b10001100 1
b100 :
b10011 8
0#
03
0)
#37
b100 <
b10011011 %
b10011011 2
b10011011 -
b10011011 ;
1#
13
b10011 7
1)
#38
b10011001 '
b10011001 1
b101 :
b10100 8
0#
03
0)
#39
b101 <
b10010011 %
b10010011 2
b10010011 -
b10010011 ;
1#
13
b10100 7
1)
#40
b10011011 '
b10011011 1
b110 :
b10101 8
0#
03
0)
0+
#41
b110 <
b10000010 %
b10000010 2
b10000010 -
b10000010 ;
1#
13
b10101 7
1)
#42
b10010011 '
b10010011 1
b111 :
b10110 8
0#
03
0)
#43
b111 <
b10010111 %
b10010111 2
b10010111 -
b10010111 ;
1#
13
b10110 7
1)
#44
b10000010 '
b10000010 1
b1000 :
b10111 8
0#
03
0)
#45
b1000 <
b10010000 %
b10010000 2
b10010000 -
b10010000 ;
1#
13
b10111 7
1)
#46
b10010111 '
b10010111 1
b1001 :
b11000 8
0#
03
0)
#47
b1001 <
b10011111 %
b10011111 2
b10011111 -
b10011111 ;
1#
13
b11000 7
1)
#48
b10010000 '
b10010000 1
b1010 :
b11001 8
0#
03
0)
#49
b1010 <
b11010111 %
b11010111 2
b11010111 -
b11010111 ;
1#
13
b11001 7
1)
#50
b10011111 '
b10011111 1
b1011 :
b11010 8
0#
03
0)
#51
b1011 <
b10001101 %
b10001101 2
b10001101 -
b10001101 ;
1#
13
b11010 7
1)
#52
b11010111 '
b11010111 1
b1100 :
b11011 8
0#
03
0)
#53
b1100 <
b10011100 %
b10011100 2
b10011100 -
b10011100 ;
1#
13
b11011 7
1)
#54
b10001101 '
b10001101 1
b1101 :
b11100 8
0#
03
0)
#55
b1101 <
b10000101 %
b10000101 2
b10000101 -
b10000101 ;
1#
13
b11100 7
1)
#56
b10011100 '
b10011100 1
b1110 :
b11101 8
0#
03
0)
#57
b1110 <
b10001010 %
b10001010 2
b10001010 -
b10001010 ;
1#
13
b11101 7
1)
#58
b10000101 '
b10000101 1
b1111 :
b11110 8
0#
03
0)
#59
b1111 <
b10010001 %
b10010001 2
b10010001 -
b10010001 ;
1#
13
b11110 7
1)
#60
b10001010 '
b10001010 1
b10000 :
b11111 8
0#
03
0)
#61
b10000 <
b10001100 %
b10001100 2
b10001100 -
b10001100 ;
1#
13
b11111 7
1)
#62
b10010001 '
b10010001 1
b10001 :
b0 8
0#
03
0)
#63
b10001 <
b10001011 %
b10001011 2
b10001011 -
b10001011 ;
1#
13
b100000 7
1)
#64
b10001100 '
b10001100 1
b10010 :
b1 8
0#
03
0)
#65
b10010 <
b10001100 %
b10001100 2
b10001100 -
b10001100 ;
1#
13
b100001 7
1)
#66
b0 &
b0 0
b10001011 '
b10001011 1
b10011 :
b10 8
0#
03
0)
#67
b10011 <
b10011001 %
b10011001 2
b10011001 -
b10011001 ;
1#
13
b100010 7
1)
#68
b10001011 &
b10001011 0
b10001100 '
b10001100 1
b10100 :
b11 8
0#
03
0)
#69
b10100 <
b10011011 %
b10011011 2
b10011011 -
b10011011 ;
1#
13
b100011 7
1)
#70
b10001100 &
b10001100 0
b10011001 '
b10011001 1
b10101 :
b100 8
0#
03
0)
#71
b10101 <
b10010011 %
b10010011 2
b10010011 -
b10010011 ;
1#
13
b100100 7
1)
#72
b10011001 &
b10011001 0
b10011011 '
b10011011 1
b10110 :
b101 8
0#
03
0)
#73
b10110 <
b10000010 %
b10000010 2
b10000010 -
b10000010 ;
1#
13
b100101 7
1)
#74
b10011011 &
b10011011 0
b10010011 '
b10010011 1
b10111 :
b110 8
0#
03
0)
#75
b10111 <
b10010111 %
b10010111 2
b10010111 -
b10010111 ;
1#
13
b100110 7
1)
#76
b10010011 &
b10010011 0
b10000010 '
b10000010 1
b11000 :
b111 8
0#
03
0)
#77
b11000 <
b10010000 %
b10010000 2
b10010000 -
b10010000 ;
1#
13
b100111 7
1)
#78
b10000010 &
b10000010 0
b10010111 '
b10010111 1
b11001 :
b1000 8
0#
03
0)
#79
b11001 <
b10011111 %
b10011111 2
b10011111 -
b10011111 ;
1#
13
b101000 7
1)
#80
b10010111 &
b10010111 0
b10010000 '
b10010000 1
b11010 :
b1001 8
0#
03
0)
#81
b11010 <
b11010111 %
b11010111 2
b11010111 -
b11010111 ;
1#
13
b101001 7
1)
#82
b10010000 &
b10010000 0
b10011111 '
b10011111 1
b11011 :
b1010 8
0#
03
0)
#83
b11011 <
b10001101 %
b10001101 2
b10001101 -
b10001101 ;
1#
13
b101010 7
1)
#84
b10011111 &
b10011111 0
b11010111 '
b11010111 1
b11100 :
b1011 8
0#
03
0)
#85
b11100 <
b10011100 %
b10011100 2
b10011100 -
b10011100 ;
1#
13
b101011 7
1)
#86
b11010111 &
b11010111 0
b10001101 '
b10001101 1
b101011 (
b101011 .
b11101 :
b1100 8
0#
03
0)
#87
b11101 <
b10000101 %
b10000101 2
b10000101 -
b10000101 ;
1#
13
b101100 7
1)
#88
b10001101 &
b10001101 0
b10011100 '
b10011100 1
b101100 (
b101100 .
b11110 :
b1101 8
0#
03
0)
#89
b11110 <
b10001010 %
b10001010 2
b10001010 -
b10001010 ;
1#
13
b101101 7
1)
#90
b10011100 &
b10011100 0
b10000101 '
b10000101 1
b11111 :
b1110 8
0#
03
0)
#91
b11111 <
b10010001 %
b10010001 2
b10010001 -
b10010001 ;
1#
13
b101110 7
1)
#92
b10000101 &
b10000101 0
b10001010 '
b10001010 1
b0 :
b1111 8
0#
03
0)
#93
b100000 <
b10001100 %
b10001100 2
b10001100 -
b10001100 ;
1#
13
b101111 7
1)
#94
b10001010 &
b10001010 0
b10010001 '
b10010001 1
b1 :
b10000 8
0#
03
0)
#95
b100001 <
b10001011 %
b10001011 2
b10001011 -
b10001011 ;
1#
13
b110000 7
1)
#96
b10010001 &
b10010001 0
b10001100 '
b10001100 1
b10 :
b10001 8
0#
03
0)
#97
b100010 <
b10001100 %
b10001100 2
b10001100 -
b10001100 ;
1#
13
b110001 7
1)
#98
b10001100 &
b10001100 0
b10001011 '
b10001011 1
b11 :
b10010 8
0#
03
0)
#99
b100011 <
b10011001 %
b10011001 2
b10011001 -
b10011001 ;
1#
13
b110010 7
1)
#100
b10001011 &
b10001011 0
b10001100 '
b10001100 1
b100 :
b10011 8
0#
03
0)
#101
b100100 <
b10011011 %
b10011011 2
b10011011 -
b10011011 ;
1#
13
b110011 7
1)
#102
b10001100 &
b10001100 0
b10011001 '
b10011001 1
b101 :
b10100 8
0#
03
0)
#103
b100101 <
b10010011 %
b10010011 2
b10010011 -
b10010011 ;
1#
13
b110100 7
1)
#104
b10011001 &
b10011001 0
b10011011 '
b10011011 1
b110 :
b10101 8
0#
03
0)
#105
b100110 <
b10000010 %
b10000010 2
b10000010 -
b10000010 ;
1#
13
b110101 7
1)
#106
b10011011 &
b10011011 0
b10010011 '
b10010011 1
b111 :
b10110 8
0#
03
0)
#107
b100111 <
b10010111 %
b10010111 2
b10010111 -
b10010111 ;
1#
13
b110110 7
1)
#108
b10010011 &
b10010011 0
b10000010 '
b10000010 1
b1000 :
b10111 8
0#
03
0)
#109
b101000 <
b10010000 %
b10010000 2
b10010000 -
b10010000 ;
1#
13
b110111 7
1)
#110
b10000010 &
b10000010 0
b10010111 '
b10010111 1
b1001 :
b11000 8
0#
03
0)
#111
b101001 <
b10011111 %
b10011111 2
b10011111 -
b10011111 ;
1#
13
b111000 7
1)
#112
b10010111 &
b10010111 0
b10010000 '
b10010000 1
b1010 :
b11001 8
0#
03
0)
#113
b101010 <
b11010111 %
b11010111 2
b11010111 -
b11010111 ;
1#
13
b111001 7
1)
#114
b10010000 &
b10010000 0
b10011111 '
b10011111 1
b1011 :
b11010 8
0#
03
0)
#115
b101011 <
b10001101 %
b10001101 2
b10001101 -
b10001101 ;
1#
13
b111010 7
1)
#116
b10011111 &
b10011111 0
b11010111 '
b11010111 1
b1100 :
b11011 8
0#
03
0)
#117
b101100 <
b10011100 %
b10011100 2
b10011100 -
b10011100 ;
1#
13
b111011 7
1)
#118
b11010111 &
b11010111 0
b10001101 '
b10001101 1
b111011 (
b111011 .
b1101 :
b11100 8
0#
03
0)
#119
b101101 <
b10000101 %
b10000101 2
b10000101 -
b10000101 ;
1#
13
b111100 7
1)
#120
b10001101 &
b10001101 0
b10011100 '
b10011100 1
b111100 (
b111100 .
b1110 :
b11101 8
0#
03
0)
#121
b101110 <
b10001010 %
b10001010 2
b10001010 -
b10001010 ;
1#
13
b111101 7
1)
#122
b10011100 &
b10011100 0
b10000101 '
b10000101 1
b1111 :
b11110 8
0#
03
0)
#123
b101111 <
b10010001 %
b10010001 2
b10010001 -
b10010001 ;
1#
13
b111110 7
1)
#124
b10000101 &
b10000101 0
b10001010 '
b10001010 1
b10000 :
b11111 8
0#
03
0)
#125
b110000 <
b10001100 %
b10001100 2
b10001100 -
b10001100 ;
1#
13
b111111 7
1)
#126
b10001010 &
b10001010 0
b10010001 '
b10010001 1
b10001 :
b0 8
0#
03
0)
#127
b110001 <
b10001011 %
b10001011 2
b10001011 -
b10001011 ;
1#
13
b1000000 7
1)
#128
b10010001 &
b10010001 0
b10001100 '
b10001100 1
b10010 :
b1 8
0#
03
0)
#129
b110010 <
b10001100 %
b10001100 2
b10001100 -
b10001100 ;
1#
13
b1000001 7
1)
#130
b10001100 &
b10001100 0
b10001011 '
b10001011 1
b10011 :
b10 8
0#
03
0)
#131
b110011 <
b10011001 %
b10011001 2
b10011001 -
b10011001 ;
1#
13
b1000010 7
1)
#132
b10001011 &
b10001011 0
b10001100 '
b10001100 1
b10100 :
b11 8
0#
03
0)
#133
b110100 <
b10011011 %
b10011011 2
b10011011 -
b10011011 ;
1#
13
b1000011 7
1)
#134
b10001100 &
b10001100 0
b10011001 '
b10011001 1
b10101 :
b100 8
0#
03
0)
#135
b110101 <
b10010011 %
b10010011 2
b10010011 -
b10010011 ;
1#
13
b1000100 7
1)
#136
b10011001 &
b10011001 0
b10011011 '
b10011011 1
b10110 :
b101 8
0#
03
0)
#137
b110110 <
b10000010 %
b10000010 2
b10000010 -
b10000010 ;
1#
13
b1000101 7
1)
#138
b10011011 &
b10011011 0
b10010011 '
b10010011 1
b10111 :
b110 8
0#
03
0)
#139
b110111 <
b10010111 %
b10010111 2
b10010111 -
b10010111 ;
1#
13
b1000110 7
1)
#140
b10010011 &
b10010011 0
b10000010 '
b10000010 1
b11000 :
b111 8
0#
03
0)
#141
b111000 <
b10010000 %
b10010000 2
b10010000 -
b10010000 ;
1#
13
b1000111 7
1)
#142
b10000010 &
b10000010 0
b10010111 '
b10010111 1
b11001 :
b1000 8
0#
03
0)
#143
b111001 <
b10011111 %
b10011111 2
b10011111 -
b10011111 ;
1#
13
b1001000 7
1)
#144
b10010111 &
b10010111 0
b10010000 '
b10010000 1
b11010 :
b1001 8
0#
03
0)
#145
b111010 <
b11010111 %
b11010111 2
b11010111 -
b11010111 ;
1#
13
b1001001 7
1)
#146
b10010000 &
b10010000 0
b10011111 '
b10011111 1
b11011 :
b1010 8
0#
03
0)
#147
b111011 <
b10001101 %
b10001101 2
b10001101 -
b10001101 ;
1#
13
b1001010 7
1)
#148
b10011111 &
b10011111 0
b11010111 '
b11010111 1
b11100 :
b1011 8
0#
03
0)
#149
b111100 <
b10011100 %
b10011100 2
b10011100 -
b10011100 ;
1#
13
b1001011 7
1)
#150
b11010111 &
b11010111 0
b10001101 '
b10001101 1
b1001011 (
b1001011 .
b11101 :
b1100 8
0#
03
0)
#151
b111101 <
b10000101 %
b10000101 2
b10000101 -
b10000101 ;
1#
13
b1001100 7
1)
#152
b10001101 &
b10001101 0
b10011100 '
b10011100 1
b1001100 (
b1001100 .
b11110 :
b1101 8
0#
03
0)
#153
b111110 <
b10001010 %
b10001010 2
b10001010 -
b10001010 ;
1#
13
b1001101 7
1)
#154
b10011100 &
b10011100 0
b10000101 '
b10000101 1
b11111 :
b1110 8
0#
03
0)
#155
b111111 <
b10010001 %
b10010001 2
b10010001 -
b10010001 ;
1#
13
b1001110 7
1)
#156
b10000101 &
b10000101 0
b10001010 '
b10001010 1
b0 :
b1111 8
0#
03
0)
#157
b1000000 <
b10001100 %
b10001100 2
b10001100 -
b10001100 ;
1#
13
b1001111 7
1)
#158
b10001010 &
b10001010 0
b10010001 '
b10010001 1
b1 :
b10000 8
0#
03
0)
#159
b1000001 <
b10001011 %
b10001011 2
b10001011 -
b10001011 ;
1#
13
b1010000 7
1)
#160
b10010001 &
b10010001 0
b10001100 '
b10001100 1
b10 :
b10001 8
0#
03
0)
#161
b1000010 <
b10001100 %
b10001100 2
b10001100 -
b10001100 ;
1#
13
b1010001 7
1)
#162
b10001100 &
b10001100 0
b10001011 '
b10001011 1
b11 :
b10010 8
0#
03
0)
#163
b1000011 <
b10011001 %
b10011001 2
b10011001 -
b10011001 ;
1#
13
b1010010 7
1)
#164
b10001011 &
b10001011 0
b10001100 '
b10001100 1
b100 :
b10011 8
0#
03
0)
#165
b1000100 <
b10011011 %
b10011011 2
b10011011 -
b10011011 ;
1#
13
b1010011 7
1)
#166
b10001100 &
b10001100 0
b10011001 '
b10011001 1
b101 :
b10100 8
0#
03
0)
#167
b1000101 <
b10010011 %
b10010011 2
b10010011 -
b10010011 ;
1#
13
b1010100 7
1)
#168
b10011001 &
b10011001 0
b10011011 '
b10011011 1
b110 :
b10101 8
0#
03
0)
#169
b1000110 <
b10000010 %
b10000010 2
b10000010 -
b10000010 ;
1#
13
b1010101 7
1)
#170
b10011011 &
b10011011 0
b10010011 '
b10010011 1
b111 :
b10110 8
0#
03
0)
#171
b1000111 <
b10010111 %
b10010111 2
b10010111 -
b10010111 ;
1#
13
b1010110 7
1)
#172
b10010011 &
b10010011 0
b10000010 '
b10000010 1
b1000 :
b10111 8
0#
03
0)
#173
b1001000 <
b10010000 %
b10010000 2
b10010000 -
b10010000 ;
1#
13
b1010111 7
1)
#174
b10000010 &
b10000010 0
b10010111 '
b10010111 1
b1001 :
b11000 8
0#
03
0)
#175
b1001001 <
b10011111 %
b10011111 2
b10011111 -
b10011111 ;
1#
13
b1011000 7
1)
#176
b10010111 &
b10010111 0
b10010000 '
b10010000 1
b1010 :
b11001 8
0#
03
0)
#177
b1001010 <
b11010111 %
b11010111 2
b11010111 -
b11010111 ;
1#
13
b1011001 7
1)
#178
b10010000 &
b10010000 0
b10011111 '
b10011111 1
b1011 :
b11010 8
0#
03
0)
#179
b1001011 <
b10001101 %
b10001101 2
b10001101 -
b10001101 ;
1#
13
b1011010 7
1)
#180
b10011111 &
b10011111 0
b11010111 '
b11010111 1
b1100 :
b11011 8
0#
03
0)
#181
b1001100 <
b10011100 %
b10011100 2
b10011100 -
b10011100 ;
1#
13
b1011011 7
1)
#182
b11010111 &
b11010111 0
b10001101 '
b10001101 1
b1011011 (
b1011011 .
b1101 :
b11100 8
0#
03
0)
#183
b1001101 <
b10000101 %
b10000101 2
b10000101 -
b10000101 ;
1#
13
b1011100 7
1)
#184
b10001101 &
b10001101 0
b10011100 '
b10011100 1
b1011100 (
b1011100 .
b1110 :
b11101 8
0#
03
0)
#185
b1001110 <
b10001010 %
b10001010 2
b10001010 -
b10001010 ;
1#
13
b1011101 7
1)
#186
b10011100 &
b10011100 0
b10000101 '
b10000101 1
b1111 :
b11110 8
0#
03
0)
#187
b1001111 <
b10010001 %
b10010001 2
b10010001 -
b10010001 ;
1#
13
b1011110 7
1)
#188
b10000101 &
b10000101 0
b10001010 '
b10001010 1
b10000 :
b11111 8
0#
03
0)
#189
b1010000 <
b10001100 %
b10001100 2
b10001100 -
b10001100 ;
1#
13
b1011111 7
1)
#190
b10001010 &
b10001010 0
b10010001 '
b10010001 1
b10001 :
b0 8
0#
03
0)
#191
b1010001 <
b10001011 %
b10001011 2
b10001011 -
b10001011 ;
1#
13
b1100000 7
1)
#192
b10010001 &
b10010001 0
b10001100 '
b10001100 1
b10010 :
b1 8
0#
03
0)
#193
b1010010 <
b10001100 %
b10001100 2
b10001100 -
b10001100 ;
1#
13
b1100001 7
1)
#194
b10001100 &
b10001100 0
b10001011 '
b10001011 1
b10011 :
b10 8
0#
03
0)
#195
b1010011 <
b10011001 %
b10011001 2
b10011001 -
b10011001 ;
1#
13
b1100010 7
1)
#196
b10001011 &
b10001011 0
b10001100 '
b10001100 1
b10100 :
b11 8
0#
03
0)
#197
b1010100 <
b10011011 %
b10011011 2
b10011011 -
b10011011 ;
1#
13
b1100011 7
1)
#198
b10001100 &
b10001100 0
b10011001 '
b10011001 1
b10101 :
b100 8
0#
03
0)
#199
b1010101 <
b10010011 %
b10010011 2
b10010011 -
b10010011 ;
1#
13
b1100100 7
1)
#200
b10011001 &
b10011001 0
b10011011 '
b10011011 1
b10110 :
b101 8
0#
03
0)
#201
b1010110 <
b10000010 %
b10000010 2
b10000010 -
b10000010 ;
1#
13
b1100101 7
1)
#202
b10011011 &
b10011011 0
b10010011 '
b10010011 1
b10111 :
b110 8
0#
03
0)
#203
b1010111 <
b10010111 %
b10010111 2
b10010111 -
b10010111 ;
1#
13
b1100110 7
1)
#204
b10010011 &
b10010011 0
b10000010 '
b10000010 1
b11000 :
b111 8
0#
03
0)
#205
b1011000 <
b10010000 %
b10010000 2
b10010000 -
b10010000 ;
1#
13
b1100111 7
1)
#206
b10000010 &
b10000010 0
b10010111 '
b10010111 1
b11001 :
b1000 8
0#
03
0)
#207
b1011001 <
b10011111 %
b10011111 2
b10011111 -
b10011111 ;
1#
13
b1101000 7
1)
#208
b10010111 &
b10010111 0
b10010000 '
b10010000 1
b11010 :
b1001 8
0#
03
0)
#209
b1011010 <
b11010111 %
b11010111 2
b11010111 -
b11010111 ;
1#
13
b1101001 7
1)
#210
b10010000 &
b10010000 0
b10011111 '
b10011111 1
b11011 :
b1010 8
0#
03
0)
#211
b1011011 <
b10001101 %
b10001101 2
b10001101 -
b10001101 ;
1#
13
b1101010 7
1)
#212
b10011111 &
b10011111 0
b11010111 '
b11010111 1
b11100 :
b1011 8
0#
03
0)
#213
b1011100 <
b10011100 %
b10011100 2
b10011100 -
b10011100 ;
1#
13
b1101011 7
1)
#214
b11010111 &
b11010111 0
b10001101 '
b10001101 1
b1101011 (
b1101011 .
b11101 :
b1100 8
0#
03
0)
#215
b1011101 <
b10000101 %
b10000101 2
b10000101 -
b10000101 ;
1#
13
b1101100 7
1)
#216
b10001101 &
b10001101 0
b10011100 '
b10011100 1
b1101100 (
b1101100 .
b11110 :
b1101 8
0#
03
0)
#217
b1011110 <
b10001010 %
b10001010 2
b10001010 -
b10001010 ;
1#
13
b1101101 7
1)
#218
b10011100 &
b10011100 0
b10000101 '
b10000101 1
b11111 :
b1110 8
0#
03
0)
#219
b1011111 <
b10010001 %
b10010001 2
b10010001 -
b10010001 ;
1#
13
b1101110 7
1)
#220
b10000101 &
b10000101 0
b10001010 '
b10001010 1
b0 :
b1111 8
0#
03
0)
#221
b1100000 <
b10001100 %
b10001100 2
b10001100 -
b10001100 ;
1#
13
b1101111 7
1)
#222
b10001010 &
b10001010 0
b10010001 '
b10010001 1
b1 :
b10000 8
0#
03
0)
#223
b1100001 <
b10001011 %
b10001011 2
b10001011 -
b10001011 ;
1#
13
b1110000 7
1)
#224
b10010001 &
b10010001 0
b10001100 '
b10001100 1
b10 :
b10001 8
0#
03
0)
#225
b1100010 <
b10001100 %
b10001100 2
b10001100 -
b10001100 ;
1#
13
b1110001 7
1)
#226
b10001100 &
b10001100 0
b10001011 '
b10001011 1
b11 :
b10010 8
0#
03
0)
#227
b1100011 <
b10011001 %
b10011001 2
b10011001 -
b10011001 ;
1#
13
b1110010 7
1)
#228
b10001011 &
b10001011 0
b10001100 '
b10001100 1
b100 :
b10011 8
0#
03
0)
#229
b1100100 <
b10011011 %
b10011011 2
b10011011 -
b10011011 ;
1#
13
b1110011 7
1)
#230
b10001100 &
b10001100 0
b10011001 '
b10011001 1
b101 :
b10100 8
0#
03
0)
#231
b1100101 <
b10010011 %
b10010011 2
b10010011 -
b10010011 ;
1#
13
b1110100 7
1)
#232
b10011001 &
b10011001 0
b10011011 '
b10011011 1
b110 :
b10101 8
0#
03
0)
#233
b1100110 <
b10000010 %
b10000010 2
b10000010 -
b10000010 ;
1#
13
b1110101 7
1)
#234
b10011011 &
b10011011 0
b10010011 '
b10010011 1
b111 :
b10110 8
0#
03
0)
#235
b1100111 <
b10010111 %
b10010111 2
b10010111 -
b10010111 ;
1#
13
b1110110 7
1)
#236
b10010011 &
b10010011 0
b10000010 '
b10000010 1
b1000 :
b10111 8
0#
03
0)
#237
b1101000 <
b10010000 %
b10010000 2
b10010000 -
b10010000 ;
1#
13
b1110111 7
1)
#238
b10000010 &
b10000010 0
b10010111 '
b10010111 1
b1001 :
b11000 8
0#
03
0)
#239
b1101001 <
b10011111 %
b10011111 2
b10011111 -
b10011111 ;
1#
13
b1111000 7
1)
#240
b10010111 &
b10010111 0
b10010000 '
b10010000 1
b1010 :
b11001 8
0#
03
0)
#241
b1101010 <
b11010111 %
b11010111 2
b11010111 -
b11010111 ;
1#
13
b1111001 7
1)
#242
b10010000 &
b10010000 0
b10011111 '
b10011111 1
b1011 :
b11010 8
0#
03
0)
#243
b1101011 <
b10001101 %
b10001101 2
b10001101 -
b10001101 ;
1#
13
b1111010 7
1)
