prac5_atempt2/adc.v
// TSC simulation module

`define VALUE_COUNT 256
  
module ADC (
    input wire req,      // Request signal from TSC
    input wire rst,      // Reset signal for ADC
    output reg rdy,      // Ready signal to indicate completion
    output reg [7:0] dat // Data output from the array
);

  reg [0:7] adc_data [0:`VALUE_COUNT-1];
  
  integer fd, i, j;// File descriptor

  initial begin
    // Open the CSV file for reading (replace "adc_data.csv" with your actual filename)
    fd = $fopen("adc_data.csv", "r");
    
    // Check if file open was successful
    if (fd == -1) begin
      $display("Error opening file!");
      $finish;  // Exit simulation on error
    end
    
    // Loop through each element of the array
    for (i = 0; i < `VALUE_COUNT; i++) begin
      // Read a line from the file
      j = $fscanf(fd, "%d", adc_data[i]);
    end

    // Close the file
    $fclose(fd);
  end

  
  
  reg [7:0] idx = 0; // Index to access the array
  

always @(posedge req or negedge req or posedge rst) begin
    if (rst) begin
        // Reset the device
        rdy <= 0;
        dat <= 8'b00000000; // Reset data output
        idx <= 0; // Reset array index
    end else if (req) begin
        // Read data from the sample array using modular arithmetic
        dat <= adc_data[idx % `VALUE_COUNT]; // Wrap around if idx exceeds 15
        idx <= idx + 1;

        // Raise RDY line
        rdy <= 1;
    end else begin
        // Lower RDY line if not processing
        rdy <= 0;
    end
end

endmodule

prac5_atempt2/TSC.v
`include "adc.v"

//state for state machine
`define STOP 3'b000 //when the machine is powered on and has not been reset yet.
`define READY 3'b001 //machine has been reset, waiting for start command
`define RUNNING 3'b010 //machine is running, incrementing the timer and writing adc values to the ring buffer
`define TRIGERED 3'b011 //the machine has been triggered, and is capturing the next 16 values
`define IDLE 3'b100 //the machine has capture the 16 values and is waiting for a start or SBF command
`define SENDING 3'b101 //the machine has received and SBF command and is sending data on the SD line.

//bit definitions for the current serial bit when transmitting data via SD line
`define WAIT_BIT 4'b1101 //wait for at least 1 posedge clk for first start bit
`define TRANSMISSION_START_BIT 4'b1110 
`define END_BIT 4'b0111 //data bytes is only has bits 0-7, so reaching bit 7 means the byte has finished.
`define START_BIT 4'b1111 //start bit of the byte transmission

module TSC (
    //control lines for this module
    input wire clk,
    input wire reset,
    input wire start,
    input wire SBF,

    //watching register for test bench

    //state machine watchers
    output reg[2:0] state_out,

    //adc watchers
    output reg adc_request_out, 
    output reg adc_ready_out,
    output reg [7:0] adc_data_out,

    //ring buffer watchers
    output reg [4:0] read_ptr_out,
    output reg [4:0] write_ptr_out,
    output reg [7:0] ring_buffer_read_ptr,
    output reg [7:0] ring_buffer_write_ptr,
    
    //trigger watchers
    output reg [4:0] remaining_values_out,
    output reg [31:0] TRIGTM_out,

    //hub module watchers
    output reg TRD_out,
    output reg SD_out,
    output reg CD_out,
    output reg [3:0] serial_bit_out
    );

// ADC MODULE
  reg adc_request = 0;
  wire adc_ready;
  wire [7:0] adc_data;

  initial begin //assign watching registers for test bench
    assign adc_request_out = adc_request;
    assign adc_ready_out = adc_ready;
    assign adc_data_out = adc_data;
  end
  
  ADC i_adc (
    .req(adc_request),
    .rst(reset),
    .rdy(adc_ready),
    .dat(adc_data)
  );

// HUB MODULE (not implemented)
  reg TRD = 1'b0; //trigger the HUB that the values can be sent.
// wire SBF; //included as a TSC module input for testing
  reg SD = 1'b0; //serial data line
  reg CD = 1'b1; //completed data line

  initial begin //assign watching registers for test bench
    assign TRD_out = TRD;
    assign SD_out = SD;
    assign CD_out = CD;
  end

// TSC MACHINE CODE

  reg [2:0] state = `STOP; //current state for state machine
  reg [31:0] timer = 32'h0000; 
  reg [31:0] TRIGTM = 32'h0000; //time when triggered
  parameter [7:0] TRIGVL = 8'hc8; //constant trigger value.
  reg [4:0] remaining_values = 5'h00; //when triggered, this will count down from 16 to grab the following 16 adc values

  reg [7:0] ring_buffer [0:31]; 
  reg [4:0] read_ptr; //the 'head' of the ring buffer
  reg [4:0] write_ptr; //the 'tail' of the ring buffer
  reg [3:0] serial_bit; //current bit in the byte (including start bit) of the byte being sent over SD line.
  
  initial begin //assign watching registers for test bench
    assign state_out = state;
    assign read_ptr_out = read_ptr;
    assign write_ptr_out = write_ptr;
    assign remaining_values_out = remaining_values;
    assign TRIGTM_out = TRIGTM;
    assign serial_bit_out = serial_bit;
  end

// POSEDGE RESET
  always @(posedge reset) begin // reset completely reset this module and the adc
    state = `READY;
    // stuff that needs to be reset here
    remaining_values = 5'h00;
    read_ptr = 5'b00000;
    write_ptr = 5'b11111;
  end

//POSEDGE START
  always @(posedge start) begin // start starts the ring buffer and timer
    if ((state == `READY) || (state == `IDLE)) begin
      timer = 32'h0000;
      TRD = 1'b0;
      state = `RUNNING;
    end
  end

//POSEDGE CLOCK
  always @(posedge clk) begin
    case(state)

      `RUNNING: begin
        timer++;
        if (~ adc_request)
          adc_request = 1; //request new adc value (handled with posedge adc_ready)
      end

      `TRIGERED: begin
        timer++;
        if(remaining_values--) begin //check that there are remaining values left to capture and decrement.
          if (~ adc_request)
            adc_request = 1; //request new adc value (handled with posedge adc_ready)
        end else begin //all 16 values have been captured, wait for start or SBF command
          state = `IDLE; 
          TRD = 1'b1;
        end
      end

      `SENDING: begin //wait 1 posedge clk for first start bit
        if (serial_bit == `WAIT_BIT) begin
          serial_bit = `TRANSMISSION_S
        TART_BIT;
        end
      end

      default:;

    endcase
  end

//NEGEDGE CLOCK
  always @(negedge clk) begin //bytes are written on negedge, and read on the posedge
    if (state == `SENDING) begin
      case(serial_bit)

        `WAIT_BIT:; //wait bit is handled by POSEDGE CLK

        `TRANSMISSION_S
    TART_BIT: begin
            serial_bit = `START_BIT  //start the transmission
            SD = 1'b0; //pull start bit low;
        ; 
        end

        `END_BIT: begin
            //usually the stop bit would go here, but instead it transitions straight to the next start bit
            serial_bit = `START_BIT
            SD = 1'b0;
        ; //serial = `TRANSMISSION_S
    TART_BIT would implement the stop bit -> start bit -> next byte

            if (read_ptr++ == write_ptr) begin //read next byte. if bytes are finished, go to ready state and put CD high
                state = `READY;
                CD = 1'b1;
            end
        end

        default: begin //handle the byte transmission;
          SD = ring_buffer[read_ptr][++serial_bit]; //send the [serial bit] bit of the current byte
        end

      endcase
    end

    ring_buffer_read_ptr <= ring_buffer[read_ptr]; //update watching register
    ring_buffer_write_ptr <= ring_buffer[write_ptr]; //update watching register
  end

//POSEDGE ADC READY
  always @(posedge adc_ready) begin
    if (adc_request) begin
      #1 //delay so the pulse doesn't disappear on the echo. TO BE REMOVED
          
      //manage trigger_value
      if (state != `TRIGERED) begin  //if it hasn't been triggered already, check for a valid trigger
        if (adc_data > TRIGVL) begin
          state = `TRIGERED;
          TRIGTM = timer; //capture time of trigger
          remaining_values = 5'h10; //set remaining adc values to 16 (handled by posedge clk)
        end
      end

      //store data and move pointers around
      ring_buffer[++write_ptr] = adc_data;
      read_ptr++;

      adc_request = 0; //pull request down

      ring_buffer_read_ptr <= ring_buffer[read_ptr]; //update watching register
      ring_buffer_write_ptr <= ring_buffer[write_ptr]; //update watching register
    end
  end

//POSEDGE SBF
  always @(posedge SBF) begin
    if (state == `IDLE) begin //wait for SBF command when in idle state
      state = `SENDING;
      SD = 1'b1;
      CD = 1'b0;
      TRD = 1'b0;
      serial_bit = `WAIT_BIT; //wait for posedge clk to start the start bit
    end
  end

endmodule

prac5_atempt2/TSC_tb.v
`timescale 1ps / 1ps
`include "TSC.v"

module TSC_tb;

  // Inputs
  reg clk; // Added clock signal
  reg reset;
  reg start;
  reg SBF;

  // OUTPUTS
  // state machine watcher
  output wire [2:0] state_out; 

  // adc watchers
  output wire adc_request_out;
  output wire adc_ready_out;
  output wire [7:0] adc_data_out;

  // ring buffer watchers
  output wire [4:0] read_ptr_out;
  output wire [4:0] write_ptr_out;
  output wire [7:0] ring_buffer_read_ptr;
  output wire [7:0] ring_buffer_write_ptr;

  // trigger watchers
  output wire [4:0] remaining_values_out;
  output wire [31:0] TRIGTM_out;

  // hub module watchers
  output wire TRD_out;
  output wire SD_out;
  output wire CD_out;
  output wire [3:0] serial_bit_out;

  integer triggered_once = 1'b0;

  // Instantiate the Unit Under Test (UUT)
  TSC uut(
    // inputs
    clk, 
    reset, 
    start, 
    SBF,

    // state machine watcher
    state_out, 
    
    // adc watchers
    adc_request_out, 
    adc_ready_out,
    adc_data_out,

    // ring buffer watchers
    read_ptr_out,
    write_ptr_out,
    ring_buffer_read_ptr,
    ring_buffer_write_ptr,

    // trigger watchers
    remaining_values_out,
    TRIGTM_out,

    // hub module watchers
    TRD_out,
    SD_out,
    CD_out,
    serial_bit_out
    );

  initial begin
    // Initialize Inputs
    $dumpfile("TSC_tb.vcd");
    $dumpvars(0, TSC_tb); // Add hello_tb to waveform dump

    //setup wires
    clk = 0;
    reset = 0;
    start = 0;
    SBF = 0;

    #4
    reset = 1;
    #4
    reset = 0;
    #4
    start = 1;
    #4
    start = 0;

    #3000; 

    $display("test complete");

    $finish; // Added $finish to end the simulation
  end

  always begin
    #2 clk = ~clk; // Generate a clock signal with a period of 20ns
    // if (clk) $display("ring_buffer_read_ptr[%d] = %d\tring_buffer_write_ptr[%d] = %d",read_ptr_out,ring_buffer_read_ptr,write_ptr_out,ring_buffer_write_ptr);
  end

  always @(posedge TRD_out) begin
    if (triggered_once) begin
      #10
      SBF = 1;
      #2
      SBF = 0;
    end else begin
        triggered_once = 1'b1;
        #10
        start = 1;
        #2
        start = 0;
    end
  end
endmodule

prac5_atempt2/TSC_tb.vcd
$date
	Mon Apr 29 11:19:39 2024
$end
$version
	Icarus Verilog
$end
$timescale
	1ps
$end
$scope module TSC_tb $end
$var wire 5 ! write_ptr_out [4:0] $end
$var wire 3 " state_out [2:0] $end
$var wire 4 # serial_bit_out [3:0] $end
$var wire 8 $ ring_buffer_write_ptr [7:0] $end
$var wire 8 % ring_buffer_read_ptr [7:0] $end
$var wire 5 & remaining_values_out [4:0] $end
$var wire 5 ' read_ptr_out [4:0] $end
$var wire 1 ( adc_request_out $end
$var wire 1 ) adc_ready_out $end
$var wire 8 * adc_data_out [7:0] $end
$var wire 32 + TRIGTM_out [31:0] $end
$var wire 1 , TRD_out $end
$var wire 1 - SD_out $end
$var wire 1 . CD_out $end
$var reg 1 / SBF $end
$var reg 1 0 clk $end
$var reg 1 1 reset $end
$var reg 1 2 start $end
$var integer 32 3 triggered_once [31:0] $end
$scope module uut $end
$var wire 1 / SBF $end
$var wire 1 0 clk $end
$var wire 1 1 reset $end
$var wire 1 2 start $end
$var wire 1 4 adc_ready $end
$var wire 8 5 adc_data [7:0] $end
$var parameter 8 6 TRIGVL $end
$var reg 1 7 CD $end
$var reg 1 . CD_out $end
$var reg 1 8 SD $end
$var reg 1 - SD_out $end
$var reg 1 9 TRD $end
$var reg 1 , TRD_out $end
$var reg 32 : TRIGTM [31:0] $end
$var reg 32 ; TRIGTM_out [31:0] $end
$var reg 8 < adc_data_out [7:0] $end
$var reg 1 ) adc_ready_out $end
$var reg 1 = adc_request $end
$var reg 1 ( adc_request_out $end
$var reg 5 > read_ptr [4:0] $end
$var reg 5 ? read_ptr_out [4:0] $end
$var reg 5 @ remaining_values [4:0] $end
$var reg 5 A remaining_values_out [4:0] $end
$var reg 8 B ring_buffer_read_ptr [7:0] $end
$var reg 8 C ring_buffer_write_ptr [7:0] $end
$var reg 4 D serial_bit [3:0] $end
$var reg 4 E serial_bit_out [3:0] $end
$var reg 3 F state [2:0] $end
$var reg 3 G state_out [2:0] $end
$var reg 32 H timer [31:0] $end
$var reg 5 I write_ptr [4:0] $end
$var reg 5 J write_ptr_out [4:0] $end
$scope module i_adc $end
$var wire 1 = req $end
$var wire 1 1 rst $end
$var reg 8 K dat [7:0] $end
$var reg 8 L idx [7:0] $end
$var reg 1 4 rdy $end
$var integer 32 M fd [31:0] $end
$var integer 32 N i [31:0] $end
$var integer 32 O j [31:0] $end
$upscope $end
$upscope $end
$upscope $end
$enddefinitions $end
$comment Show the parameter values. $end
$dumpall
b11001000 6
$end
#0
$dumpvars
b0 O
b100000000 N
b10000000000000000000000000000011 M
b0 L
bx K
bx J
bx I
b0 H
b0 G
b0 F
bx E
bx D
bx C
bx B
b0 A
b0 @
bx ?
bx >
0=
bx <
b0 ;
b0 :
09
08
17
bx 5
04
b0 3
02
01
00
0/
1.
0-
0,
b0 +
bx *
0)
0(
bx '
b0 &
bx %
bx $
bx #
b0 "
bx !
$end
#2
10
#4
b0 *
b0 <
b0 5
b0 K
b11111 !
b11111 J
b11111 I
b0 '
b0 ?
b0 >
b1 "
b1 G
b1 F
00
11
#6
10
#8
00
01
#10
10
#12
b10 "
b10 G
b10 F
00
12
#14
1)
14
b1 L
b10100000 *
b10100000 <
b10100000 5
b10100000 K
1(
1=
b1 H
10
#15
0)
04
b10100000 $
b10100000 C
0(
0=
b1 '
b1 ?
b1 >
b0 !
b0 J
b0 I
#16
00
02
#18
1)
14
b10 L
b110101 *
b110101 <
b110101 5
b110101 K
1(
1=
b10 H
10
#19
0)
04
b110101 $
b110101 C
0(
0=
b10 '
b10 ?
b10 >
b1 !
b1 J
b1 I
#20
00
#22
1)
14
b11 L
b1011 *
b1011 <
b1011 5
b1011 K
1(
1=
b11 H
10
#23
0)
04
b1011 $
b1011 C
0(
0=
b11 '
b11 ?
b11 >
b10 !
b10 J
b10 I
#24
00
#26
1)
14
b100 L
b111101 *
b111101 <
b111101 5
b111101 K
1(
1=
b100 H
10
#27
0)
04
b111101 $
b111101 C
0(
0=
b100 '
b100 ?
b100 >
b11 !
b11 J
b11 I
#28
00
#30
1)
14
b101 L
b111111 *
b111111 <
b111111 5
b111111 K
1(
1=
b101 H
10
#31
0)
04
b111111 $
b111111 C
0(
0=
b101 '
b101 ?
b101 >
b100 !
b100 J
b100 I
#32
00
#34
1)
14
b110 L
b1000011 *
b1000011 <
b1000011 5
b1000011 K
1(
1=
b110 H
10
#35
0)
04
b1000011 $
b1000011 C
0(
0=
b110 '
b110 ?
b110 >
b101 !
b101 J
b101 I
#36
00
#38
1)
14
b111 L
b1101110 *
b1101110 <
b1101110 5
b1101110 K
1(
1=
b111 H
10
#39
0)
04
b1101110 $
b1101110 C
0(
0=
b111 '
b111 ?
b111 >
b110 !
b110 J
b110 I
#40
00
#42
1)
14
b1000 L
b1010011 *
b1010011 <
b1010011 5
b1010011 K
1(
1=
b1000 H
10
#43
0)
04
b1010011 $
b1010011 C
0(
0=
b1000 '
b1000 ?
b1000 >
b111 !
b111 J
b111 I
#44
00
#46
1)
14
b1001 L
b10000001 *
b10000001 <
b10000001 5
b10000001 K
1(
1=
b1001 H
10
#47
0)
04
b10000001 $
b10000001 C
0(
0=
b1001 '
b1001 ?
b1001 >
b1000 !
b1000 J
b1000 I
#48
00
#50
1)
14
b1010 L
b1100010 *
b1100010 <
b1100010 5
b1100010 K
1(
1=
b1010 H
10
#51
0)
04
b1100010 $
b1100010 C
0(
0=
b1010 '
b1010 ?
b1010 >
b1001 !
b1001 J
b1001 I
#52
00
#54
1)
14
b1011 L
b10010101 *
b10010101 <
b10010101 5
b10010101 K
1(
1=
b1011 H
10
#55
0)
04
b10010101 $
b10010101 C
0(
0=
b1011 '
b1011 ?
b1011 >
b1010 !
b1010 J
b1010 I
#56
00
#58
1)
14
b1100 L
b1110011 *
b1110011 <
b1110011 5
b1110011 K
1(
1=
b1100 H
10
#59
0)
04
b1110011 $
b1110011 C
0(
0=
b1100 '
b1100 ?
b1100 >
b1011 !
b1011 J
b1011 I
#60
00
#62
1)
14
b1101 L
b10000110 *
b10000110 <
b10000110 5
b10000110 K
1(
1=
b1101 H
10
#63
0)
04
b10000110 $
b10000110 C
0(
0=
b1101 '
b1101 ?
b1101 >
b1100 !
b1100 J
b1100 I
#64
00
#66
1)
14
b1110 L
b1010 *
b1010 <
b1010 5
b1010 K
1(
1=
b1110 H
10
#67
0)
04
b1010 $
b1010 C
0(
0=
b1110 '
b1110 ?
b1110 >
b1101 !
b1101 J
b1101 I
#68
00
#70
1)
14
b1111 L
b111001 *
b111001 <
b111001 5
b111001 K
1(
1=
b1111 H
10
#71
0)
04
b111001 $
b111001 C
0(
0=
b1111 '
b1111 ?
b1111 >
b1110 !
b1110 J
b1110 I
#72
00
#74
1)
14
b10000 L
b10010111 *
b10010111 <
b10010111 5
b10010111 K
1(
1=
b10000 H
10
#75
0)
04
b10010111 $
b10010111 C
0(
0=
b10000 '
b10000 ?
b10000 >
b1111 !
b1111 J
b1111 I
#76
00
#78
1)
14
b10001 L
b10000001 *
b10000001 <
b10000001 5
b10000001 K
1(
1=
b10001 H
10
#79
0)
04
b10000001 $
b10000001 C
0(
0=
b10001 '
b10001 ?
b10001 >
b10000 !
b10000 J
b10000 I
#80
00
#82
1)
14
b10010 L
b1011000 *
b1011000 <
b1011000 5
b1011000 K
1(
1=
b10010 H
10
#83
0)
04
b1011000 $
b1011000 C
0(
0=
b10010 '
b10010 ?
b10010 >
b10001 !
b10001 J
b10001 I
#84
00
#86
1)
14
b10011 L
b100001 *
b100001 <
b100001 5
b100001 K
1(
1=
b10011 H
10
#87
0)
04
b100001 $
b100001 C
0(
0=
b10011 '
b10011 ?
b10011 >
b10010 !
b10010 J
b10010 I
#88
00
#90
1)
14
b10100 L
b111110 *
b111110 <
b111110 5
b111110 K
1(
1=
b10100 H
10
#91
0)
04
b111110 $
b111110 C
0(
0=
b10100 '
b10100 ?
b10100 >
b10011 !
b10011 J
b10011 I
#92
00
#94
1)
14
b10101 L
b10001101 *
b10001101 <
b10001101 5
b10001101 K
1(
1=
b10101 H
10
#95
0)
04
b10001101 $
b10001101 C
0(
0=
b10101 '
b10101 ?
b10101 >
b10100 !
b10100 J
b10100 I
#96
00
#98
1)
14
b10110 L
b10110001 *
b10110001 <
b10110001 5
b10110001 K
1(
1=
b10110 H
10
#99
0)
04
b10110001 $
b10110001 C
0(
0=
b10110 '
b10110 ?
b10110 >
b10101 !
b10101 J
b10101 I
#100
00
#102
1)
14
b10111 L
b1111110 *
b1111110 <
b1111110 5
b1111110 K
1(
1=
b10111 H
10
#103
0)
04
b1111110 $
b1111110 C
0(
0=
b10111 '
b10111 ?
b10111 >
b10110 !
b10110 J
b10110 I
#104
00
#106
1)
14
b11000 L
b10111001 *
b10111001 <
b10111001 5
b10111001 K
1(
1=
b11000 H
10
#107
0)
04
b10111001 $
b10111001 C
0(
0=
b11000 '
b11000 ?
b11000 >
b10111 !
b10111 J
b10111 I
#108
00
#110
1)
14
b11001 L
b1010001 *
b1010001 <
b1010001 5
b1010001 K
1(
1=
b11001 H
10
#111
0)
04
b1010001 $
b1010001 C
0(
0=
b11001 '
b11001 ?
b11001 >
b11000 !
b11000 J
b11000 I
#112
00
#114
1)
14
b11010 L
b11000101 *
b11000101 <
b11000101 5
b11000101 K
1(
1=
b11010 H
10
#115
0)
04
b11000101 $
b11000101 C
0(
0=
b11010 '
b11010 ?
b11010 >
b11001 !
b11001 J
b11001 I
#116
00
#118
1)
14
b11011 L
b1000100 *
b1000100 <
b1000100 5
b1000100 K
1(
1=
b11011 H
10
#119
0)
04
b1000100 $
b1000100 C
0(
0=
b11011 '
b11011 ?
b11011 >
b11010 !
b11010 J
b11010 I
#120
00
#122
1)
14
b11100 L
b1110011 *
b1110011 <
b1110011 5
b1110011 K
1(
1=
b11100 H
10
#123
0)
04
b1110011 $
b1110011 C
0(
0=
b11100 '
b11100 ?
b11100 >
b11011 !
b11011 J
b11011 I
#124
00
#126
1)
14
b11101 L
b1 *
b1 <
b1 5
b1 K
1(
1=
b11101 H
10
#127
0)
04
b1 $
b1 C
0(
0=
b11101 '
b11101 ?
b11101 >
b11100 !
b11100 J
b11100 I
#128
00
#130
1)
14
b11110 L
b11001 *
b11001 <
b11001 5
b11001 K
1(
1=
b11110 H
10
#131
0)
04
b11001 $
b11001 C
0(
0=
b11110 '
b11110 ?
b11110 >
b11101 !
b11101 J
b11101 I
#132
00
#134
1)
14
b11111 L
b10000100 *
b10000100 <
b10000100 5
b10000100 K
1(
1=
b11111 H
10
#135
0)
04
b10000100 $
b10000100 C
0(
0=
b11111 '
b11111 ?
b11111 >
b11110 !
b11110 J
b11110 I
#136
00
#138
1)
14
b100000 L
b101001 *
b101001 <
b101001 5
b101001 K
1(
1=
b100000 H
10
#139
0)
04
b101001 $
b101001 C
b10100000 %
b10100000 B
0(
0=
b0 '
b0 ?
b0 >
b11111 !
b11111 J
b11111 I
#140
00
#142
1)
14
b100001 L
b10011 *
b10011 <
b10011 5
b10011 K
1(
1=
b100001 H
10
#143
0)
04
b10011 $
b10011 C
b110101 %
b110101 B
0(
0=
b1 '
b1 ?
b1 >
b0 !
b0 J
b0 I
#144
00
#146
1)
14
b100010 L
b1011110 *
b1011110 <
b1011110 5
b1011110 K
1(
1=
b100010 H
10
#147
0)
04
b1011110 $
b1011110 C
b1011 %
b1011 B
0(
0=
b10 '
b10 ?
b10 >
b1 !
b1 J
b1 I
#148
00
#150
1)
14
b100011 L
b1111001 *
b1111001 <
b1111001 5
b1111001 K
1(
1=
b100011 H
10
#151
0)
04
b1111001 $
b1111001 C
b111101 %
b111101 B
0(
0=
b11 '
b11 ?
b11 >
b10 !
b10 J
b10 I
#152
00
#154
1)
14
b100100 L
b1110 *
b1110 <
b1110 5
b1110 K
1(
1=
b100100 H
10
#155
0)
04
b1110 $
b1110 C
b111111 %
b111111 B
0(
0=
b100 '
b100 ?
b100 >
b11 !
b11 J
b11 I
#156
00
#158
1)
14
b100101 L
b11 *
b11 <
b11 5
b11 K
1(
1=
b100101 H
10
#159
0)
04
b11 $
b11 C
b1000011 %
b1000011 B
0(
0=
b101 '
b101 ?
b101 >
b100 !
b100 J
b100 I
#160
00
#162
1)
14
b100110 L
b1011 *
b1011 <
b1011 5
b1011 K
1(
1=
b100110 H
10
#163
0)
04
b1011 $
b1011 C
b1101110 %
b1101110 B
0(
0=
b110 '
b110 ?
b110 >
b101 !
b101 J
b101 I
#164
00
#166
1)
14
b100111 L
b1001 *
b1001 <
b1001 5
b1001 K
1(
1=
b100111 H
10
#167
0)
04
b1001 $
b1001 C
b1010011 %
b1010011 B
0(
0=
b111 '
b111 ?
b111 >
b110 !
b110 J
b110 I
#168
00
#170
1)
14
b101000 L
b111110 *
b111110 <
b111110 5
b111110 K
1(
1=
b101000 H
10
#171
0)
04
b111110 $
b111110 C
b10000001 %
b10000001 B
0(
0=
b1000 '
b1000 ?
b1000 >
b111 !
b111 J
b111 I
#172
00
#174
1)
14
b101001 L
b100100 *
b100100 <
b100100 5
b100100 K
1(
1=
b101001 H
10
#175
0)
04
b100100 $
b100100 C
b1100010 %
b1100010 B
0(
0=
b1001 '
b1001 ?
b1001 >
b1000 !
b1000 J
b1000 I
#176
00
#178
1)
14
b101010 L
b1011011 *
b1011011 <
b1011011 5
b1011011 K
1(
1=
b101010 H
10
#179
0)
04
b1011011 $
b1011011 C
b10010101 %
b10010101 B
0(
0=
b1010 '
b1010 ?
b1010 >
b1001 !
b1001 J
b1001 I
#180
00
#182
1)
14
b101011 L
b10000000 *
b10000000 <
b10000000 5
b10000000 K
1(
1=
b101011 H
10
#183
0)
04
b10000000 $
b10000000 C
b1110011 %
b1110011 B
0(
0=
b1011 '
b1011 ?
b1011 >
b1010 !
b1010 J
b1010 I
#184
00
#186
1)
14
b101100 L
b11001 *
b11001 <
b11001 5
b11001 K
1(
1=
b101100 H
10
#187
0)
04
b11001 $
b11001 C
b10000110 %
b10000110 B
0(
0=
b1100 '
b1100 ?
b1100 >
b1011 !
b1011 J
b1011 I
#188
00
#190
1)
14
b101101 L
b1110011 *
b1110011 <
b1110011 5
b1110011 K
1(
1=
b101101 H
10
#191
0)
04
b1110011 $
b1110011 C
b1010 %
b1010 B
0(
0=
b1101 '
b1101 ?
b1101 >
b1100 !
b1100 J
b1100 I
#192
00
#194
1)
14
b101110 L
b101110 *
b101110 <
b101110 5
b101110 K
1(
1=
b101110 H
10
#195
0)
04
b101110 $
b101110 C
b111001 %
b111001 B
0(
0=
b1110 '
b1110 ?
b1110 >
b1101 !
b1101 J
b1101 I
#196
00
#198
1)
14
b101111 L
1(
1=
b101111 H
10
#199
0)
04
b10010111 %
b10010111 B
0(
0=
b1111 '
b1111 ?
b1111 >
b1110 !
b1110 J
b1110 I
#200
00
#202
1)
14
b110000 L
b1110010 *
b1110010 <
b1110010 5
b1110010 K
1(
1=
b110000 H
10
#203
0)
04
b1110010 $
b1110010 C
b10000001 %
b10000001 B
0(
0=
b10000 '
b10000 ?
b10000 >
b1111 !
b1111 J
b1111 I
#204
00
#206
1)
14
b110001 L
b110 *
b110 <
b110 5
b110 K
1(
1=
b110001 H
10
#207
0)
04
b110 $
b110 C
b1011000 %
b1011000 B
0(
0=
b10001 '
b10001 ?
b10001 >
b10000 !
b10000 J
b10000 I
#208
00
#210
1)
14
b110010 L
b10001011 *
b10001011 <
b10001011 5
b10001011 K
1(
1=
b110010 H
10
#211
0)
04
b10001011 $
b10001011 C
b100001 %
b100001 B
0(
0=
b10010 '
b10010 ?
b10010 >
b10001 !
b10001 J
b10001 I
#212
00
#214
1)
14
b110011 L
b10101110 *
b10101110 <
b10101110 5
b10101110 K
1(
1=
b110011 H
10
#215
0)
04
b10101110 $
b10101110 C
b111110 %
b111110 B
0(
0=
b10011 '
b10011 ?
b10011 >
b10010 !
b10010 J
b10010 I
#216
00
#218
1)
14
b110100 L
b11000100 *
b11000100 <
b11000100 5
b11000100 K
1(
1=
b110100 H
10
#219
0)
04
b11000100 $
b11000100 C
b10001101 %
b10001101 B
0(
0=
b10100 '
b10100 ?
b10100 >
b10011 !
b10011 J
b10011 I
#220
00
#222
1)
14
b110101 L
b10001101 *
b10001101 <
b10001101 5
b10001101 K
1(
1=
b110101 H
10
#223
0)
04
b10001101 $
b10001101 C
b10110001 %
b10110001 B
0(
0=
b10101 '
b10101 ?
b10101 >
b10100 !
b10100 J
b10100 I
#224
00
#226
1)
14
b110110 L
b110011 *
b110011 <
b110011 5
b110011 K
1(
1=
b110110 H
10
#227
0)
04
b110011 $
b110011 C
b1111110 %
b1111110 B
0(
0=
b10110 '
b10110 ?
b10110 >
b10101 !
b10101 J
b10101 I
#228
00
#230
1)
14
b110111 L
b10011111 *
b10011111 <
b10011111 5
b10011111 K
1(
1=
b110111 H
10
#231
0)
04
b10011111 $
b10011111 C
b10111001 %
b10111001 B
0(
0=
b10111 '
b10111 ?
b10111 >
b10110 !
b10110 J
b10110 I
#232
00
#234
1)
14
b111000 L
b1001001 *
b1001001 <
b1001001 5
b1001001 K
1(
1=
b111000 H
10
#235
0)
04
b1001001 $
b1001001 C
b1010001 %
b1010001 B
0(
0=
b11000 '
b11000 ?
b11000 >
b10111 !
b10111 J
b10111 I
#236
00
#238
1)
14
b111001 L
b110011 *
b110011 <
b110011 5
b110011 K
1(
1=
b111001 H
10
#239
0)
04
b110011 $
b110011 C
b11000101 %
b11000101 B
0(
0=
b11001 '
b11001 ?
b11001 >
b11000 !
b11000 J
b11000 I
#240
00
#242
1)
14
b111010 L
b1110101 *
b1110101 <
b1110101 5
b1110101 K
1(
1=
b111010 H
10
#243
0)
04
b1110101 $
b1110101 C
b1000100 %
b1000100 B
0(
0=
b11010 '
b11010 ?
b11010 >
b11001 !
b11001 J
b11001 I
#244
00
#246
1)
14
b111011 L
b111100 *
b111100 <
b111100 5
b111100 K
1(
1=
b111011 H
10
#247
0)
04
b111100 $
b111100 C
b1110011 %
b1110011 B
0(
0=
b11011 '
b11011 ?
b11011 >
b11010 !
b11010 J
b11010 I
#248
00
#250
1)
14
b111100 L
b1011111 *
b1011111 <
b1011111 5
b1011111 K
1(
1=
b111100 H
10
#251
0)
04
b1011111 $
b1011111 C
b1 %
b1 B
0(
0=
b11100 '
b11100 ?
b11100 >
b11011 !
b11011 J
b11011 I
#252
00
#254
1)
14
b111101 L
b1100 *
b1100 <
b1100 5
b1100 K
1(
1=
b111101 H
10
#255
0)
04
b1100 $
b1100 C
b11001 %
b11001 B
0(
0=
b11101 '
b11101 ?
b11101 >
b11100 !
b11100 J
b11100 I
#256
00
#258
1)
14
b111110 L
b10100100 *
b10100100 <
b10100100 5
b10100100 K
1(
1=
b111110 H
10
#259
0)
04
b10100100 $
b10100100 C
b10000100 %
b10000100 B
0(
0=
b11110 '
b11110 ?
b11110 >
b11101 !
b11101 J
b11101 I
#260
00
#262
1)
14
b111111 L
b10011 *
b10011 <
b10011 5
b10011 K
1(
1=
b111111 H
10
#263
0)
04
b10011 $
b10011 C
b101001 %
b101001 B
0(
0=
b11111 '
b11111 ?
b11111 >
b11110 !
b11110 J
b11110 I
#264
00
#266
1)
14
b1000000 L
b101 *
b101 <
b101 5
b101 K
1(
1=
b1000000 H
10
#267
0)
04
b101 $
b101 C
b10011 %
b10011 B
0(
0=
b0 '
b0 ?
b0 >
b11111 !
b11111 J
b11111 I
#268
00
#270
1)
14
b1000001 L
b10110001 *
b10110001 <
b10110001 5
b10110001 K
1(
1=
b1000001 H
10
#271
0)
04
b10110001 $
b10110001 C
b1011110 %
b1011110 B
0(
0=
b1 '
b1 ?
b1 >
b0 !
b0 J
b0 I
#272
00
#274
1)
14
b1000010 L
b1100100 *
b1100100 <
b1100100 5
b1100100 K
1(
1=
b1000010 H
10
#275
0)
04
b1100100 $
b1100100 C
b1111001 %
b1111001 B
0(
0=
b10 '
b10 ?
b10 >
b1 !
b1 J
b1 I
#276
00
#278
1)
14
b1000011 L
b10101010 *
b10101010 <
b10101010 5
b10101010 K
1(
1=
b1000011 H
10
#279
0)
04
b10101010 $
b10101010 C
b1110 %
b1110 B
0(
0=
b11 '
b11 ?
b11 >
b10 !
b10 J
b10 I
#280
00
#282
1)
14
b1000100 L
b1010001 *
b1010001 <
b1010001 5
b1010001 K
1(
1=
b1000100 H
10
#283
0)
04
b1010001 $
b1010001 C
b11 %
b11 B
0(
0=
b100 '
b100 ?
b100 >
b11 !
b11 J
b11 I
