prac5_atempt2/adc.v
// TSC simulation module

`define VALUE_COUNT 256
  
module ADC (
    input wire req,      // Request signal from TSC
    input wire rst,      // Reset signal for ADC
    output reg rdy,      // Ready signal to indicate completion
    output reg [7:0] dat // Data output from the array
);

  reg [0:7] adc_data [0:`VALUE_COUNT-1];
  
  integer fd, i, j;// File descriptor

  initial begin
    // Open the CSV file for reading (replace "adc_data.csv" with your actual filename)
    fd = $fopen("adc_data.csv", "r");
    
    // Check if file open was successful
    if (fd == -1) begin
      $display("Error opening file!");
      $finish;  // Exit simulation on error
    end
    
    // Loop through each element of the array
    for (i = 0; i < `VALUE_COUNT; i++) begin
      // Read a line from the file
      j = $fscanf(fd, "%d", adc_data[i]);
    end

    // Close the file
    $fclose(fd);
  end

  
  
  reg [7:0] idx = 0; // Index to access the array
  

always @(posedge req or negedge req or posedge rst) begin
    if (rst) begin
        // Reset the device
        rdy <= 0;
        dat <= 8'b00000000; // Reset data output
        idx <= 0; // Reset array index
    end else if (req) begin
        // Read data from the sample array using modular arithmetic
        dat <= adc_data[idx % `VALUE_COUNT]; // Wrap around if idx exceeds 15
        idx <= idx + 1;

        // Raise RDY line
        rdy <= 1;
    end else begin
        // Lower RDY line if not processing
        rdy <= 0;
    end
end

endmodule

prac5_atempt2/TSC.v
`include "adc.v"

//state for state machine
`define STOP 3'b000 //when the machine is powered on and has not been reset yet.
`define READY 3'b001 //machine has been reset, waiting for start command
`define RUNNING 3'b010 //machine is running, incrementing the timer and writing adc values to the ring buffer
`define TRIGERED 3'b011 //the machine has been triggered, and is capturing the next 16 values
`define IDLE 3'b100 //the machine has capture the 16 values and is waiting for a start or SBF command
`define SENDING 3'b101 //the machine has received and SBF command and is sending data on the SD line.

//bit definitions for the current serial bit when transmitting data via SD line
`define WAIT_BIT 4'b1110 //wait for at least 1 posedge clk for first start bit
`define START_BIT 4'b1111 //start bit
`define END_BIT 4'b1000 //data bytes is only has bits 0-7, so reaching bit 8 means the byte has finished.

module TSC (
    input wire clk,
    input wire reset,
    input wire start,
    input wire SBF,
    output reg[2:0] state_out,
    output reg adc_request_out, 
    output reg adc_ready_out,
    output reg [7:0] adc_data_out,
    output reg [4:0] read_ptr_out,
    output reg [4:0] write_ptr_out,
    output reg [7:0] ring_buffer_read_ptr,
    output reg [7:0] ring_buffer_write_ptr,
    output reg [4:0] remaining_values_out,
    output reg TRD_out,
    output reg SD_out,
    output reg CD_out
    );

// ADC MODULE
  reg adc_request = 0;
  wire adc_ready;
  wire [7:0] adc_data;

  initial begin //assign watching registers for test bench
    assign adc_request_out = adc_request;
    assign adc_ready_out = adc_ready;
    assign adc_data_out = adc_data;
  end
  
  ADC i_adc (
    .req(adc_request),
    .rst(reset),
    .rdy(adc_ready),
    .dat(adc_data)
  );

// HUB MODULE (not implemented)
  reg TRD = 1'b0; //trigger the HUB that the values can be sent.
// wire SBF; //included as a TSC module input for testing
  reg SD = 1'b0; //serial data line
  reg CD = 1'b1; //completed data line

  initial begin //assign watching registers for test bench
    assign TRD_out = TRD;
    assign SD_out = SD;
    assign CD_out = CD;
  end

// TSC MACHINE CODE

  reg [2:0] state = `STOP; //current state for state machine
  reg [31:0] timer = 32'h0000; 
  reg [31:0] TRIGTM = 32'h0000; //time when triggered
  parameter [7:0] TRIGVL = 210; //constant trigger value.
  reg [4:0] remaining_values = 5'h00; //when triggered, this will count down from 16 to grab the following 16 adc values

  reg [7:0] ring_buffer [0:31]; 
  reg [4:0] read_ptr; //the 'head' of the ring buffer
  reg [4:0] write_ptr; //the 'tail' of the ring buffer
  reg [3:0] serial_bit; //current bit in the byte (including start bit) of the byte being sent over SD line.
  
  initial begin //assign watching registers for test bench
    assign state_out = state;
    assign read_ptr_out = read_ptr;
    assign write_ptr_out = write_ptr;
    assign remaining_values_out = remaining_values;
  end

// POSEDGE RESET
  always @(posedge reset) begin // reset completely reset this module and the adc
    state = `READY;
    // stuff that needs to be reset here
    remaining_values = 5'h00;
    read_ptr = 5'b00000;
    write_ptr = 5'b11111;
  end

//POSEDGE START
  always @(posedge start) begin // start starts the ring buffer and timer
    if ((state == `READY) || (state == `IDLE)) begin
      timer = 32'h0000;
      TRD = 1'b0;
      state = `RUNNING;
    end
  end

//POSEDGE CLOCK
  always @(posedge clk) begin
    case(state)

      `RUNNING: begin
        timer++;
        if (~ adc_request)
          adc_request = 1; //request new adc value (handled with posedge adc_ready)
      end

      `TRIGERED: begin
        timer++;
        if(remaining_values--) begin //check that there are remaining values left to capture and decrement.
          if (~ adc_request)
            adc_request = 1; //request new adc value (handled with posedge adc_ready)
        end else begin //all 16 values have been captured, wait for start or SBF command
          state = `IDLE; 
          TRD = 1'b1;
        end
      end

      `SENDING: begin //wait 1 posedge clk for first start bit
        if (serial_bit == `WAIT_BIT) begin
          serial_bit = `START_BIT;
        end
      end

      default:;

    endcase
  end

//NEGEDGE CLOCK
  always @(negedge clk) begin //bytes are written on negedge, and read on the posedge
    if (state == `SENDING) begin
      case(serial_bit)

        `WAIT_BIT:; //wait bit is handled by POSEDGE CLK

        `START_BIT: begin
            SD = 1'b0; //pull start bit low;
            serial_bit = 0; //start the transmission
        end

        `END_BIT: begin
            //usually the stop bit would go here, but instead it transitions straight to the next stop bit
            SD = 1'b0;
            serial_bit = 0; //serial = `START_BIT would implement the stop bit -> start bit -> next byte

            if (read_ptr++ == write_ptr) begin //read next byte. if bytes are finished, go to ready state and put CD high
                state = `READY;
                CD = 1'b1;
            end
        end

        default: begin //handle the byte transmission;
          SD = ring_buffer[read_ptr][serial_bit++]; //send the [serial bit] bit of the current byte
        end

      endcase
    end

    ring_buffer_read_ptr <= ring_buffer[read_ptr]; //update watching register
    ring_buffer_write_ptr <= ring_buffer[write_ptr]; //update watching register
  end

//POSEDGE ADC READY
  always @(posedge adc_ready) begin
    if (adc_request) begin
      #1 //delay so the pulse doesn't disappear on the echo. TO BE REMOVED
          
      //manage trigger_value
      if (state != `TRIGERED) begin  //if it hasn't been triggered already, check for a valid trigger
        if (adc_data > TRIGVL) begin
          state = `TRIGERED;
          TRIGTM = timer; //capture time of trigger
          remaining_values = 5'h10; //set remaining adc values to 16 (handled by posedge clk)
        end
      end

      //store data and move pointers around
      ring_buffer[++write_ptr] = adc_data;
      read_ptr++;

      adc_request = 0; //pull request down
    end
  end

//POSEDGE SBF
  always @(posedge SBF) begin
    if (state == `IDLE) begin //wait for SBF command when in idle state
      state = `SENDING;
      SD = 1'b1;
      CD = 1'b0;
      serial_bit = `WAIT_BIT; //wait for posedge clk to start the start bit
    end
  end

endmodule

prac5_atempt2/TSC_tb.v
`timescale 1ps / 1ps
`include "TSC.v"

module TSC_tb;

  // Inputs
  reg clk; // Added clock signal
  reg reset;
  reg start;
  reg SBF;
//   reg SBF;

  // Outputs
  output wire [2:0] state;

  output wire adc_request_out;
  output wire adc_ready_out;
  output wire [7:0] adc_data_out;

  output wire [4:0] read_ptr_out;
  output wire [4:0] write_ptr_out;
  output wire [7:0] ring_buffer_read_ptr;
  output wire [7:0] ring_buffer_write_ptr;

  output wire [4:0] remaining_values_out;

  output wire TRD_out;
  output wire SD_out;
  output wire CD_out;

  // Instantiate the Unit Under Test (UUT)
  TSC uut(
    clk, 
    reset, 
    start, 
    SBF,
    state, 
    adc_request_out, 
    adc_ready_out,
    adc_data_out,
    read_ptr_out,
    write_ptr_out,
    ring_buffer_read_ptr,
    ring_buffer_write_ptr,
    remaining_values_out,
    TRD_out,
    SD_out,
    CD_out
    );

  initial begin
    // Initialize Inputs
    $dumpfile("TSC_tb.vcd");
    $dumpvars(0, TSC_tb); // Add hello_tb to waveform dump

    clk = 0;
    reset = 0;
    start = 0;
    SBF = 0;
    // SBF = 0;
    #4
    reset = 1;
    #4
    reset = 0;
    #4
    start = 1;
    #4
    start = 0;
    #2000; 

    $display("test complete");

    $finish; // Added $finish to end the simulation
  end

  always begin
    #2 clk = ~clk; // Generate a clock signal with a period of 20ns
    if (clk) $display("ring_buffer_read_ptr[%d] = %d\tring_buffer_write_ptr[%d] = %d",read_ptr_out,ring_buffer_read_ptr,write_ptr_out,ring_buffer_write_ptr);
  end

  always @(posedge TRD_out) begin
    #20 
    SBF = 1;
    #2
    SBF = 0;
  end
endmodule

prac5_atempt2/TSC_tb.vcd
$date
	Sun Apr 28 20:36:19 2024
$end
$version
	Icarus Verilog
$end
$timescale
	1ps
$end
$scope module TSC_tb $end
$var wire 5 ! write_ptr_out [4:0] $end
$var wire 3 " state [2:0] $end
$var wire 8 # ring_buffer_write_ptr [7:0] $end
$var wire 8 $ ring_buffer_read_ptr [7:0] $end
$var wire 5 % remaining_values_out [4:0] $end
$var wire 5 & read_ptr_out [4:0] $end
$var wire 1 ' adc_request_out $end
$var wire 1 ( adc_ready_out $end
$var wire 8 ) adc_data_out [7:0] $end
$var wire 1 * TRD_out $end
$var wire 1 + SD_out $end
$var wire 1 , CD_out $end
$var reg 1 - SBF $end
$var reg 1 . clk $end
$var reg 1 / reset $end
$var reg 1 0 start $end
$scope module uut $end
$var wire 1 - SBF $end
$var wire 1 . clk $end
$var wire 1 / reset $end
$var wire 1 0 start $end
$var wire 1 1 adc_ready $end
$var wire 8 2 adc_data [7:0] $end
$var parameter 8 3 TRIGVL $end
$var reg 1 4 CD $end
$var reg 1 , CD_out $end
$var reg 1 5 SD $end
$var reg 1 + SD_out $end
$var reg 1 6 TRD $end
$var reg 1 * TRD_out $end
$var reg 32 7 TRIGTM [31:0] $end
$var reg 8 8 adc_data_out [7:0] $end
$var reg 1 ( adc_ready_out $end
$var reg 1 9 adc_request $end
$var reg 1 ' adc_request_out $end
$var reg 5 : read_ptr [4:0] $end
$var reg 5 ; read_ptr_out [4:0] $end
$var reg 5 < remaining_values [4:0] $end
$var reg 5 = remaining_values_out [4:0] $end
$var reg 8 > ring_buffer_read_ptr [7:0] $end
$var reg 8 ? ring_buffer_write_ptr [7:0] $end
$var reg 4 @ serial_bit [3:0] $end
$var reg 3 A state [2:0] $end
$var reg 3 B state_out [2:0] $end
$var reg 32 C timer [31:0] $end
$var reg 5 D write_ptr [4:0] $end
$var reg 5 E write_ptr_out [4:0] $end
$scope module i_adc $end
$var wire 1 9 req $end
$var wire 1 / rst $end
$var reg 8 F dat [7:0] $end
$var reg 8 G idx [7:0] $end
$var reg 1 1 rdy $end
$var integer 32 H fd [31:0] $end
$var integer 32 I i [31:0] $end
$var integer 32 J j [31:0] $end
$upscope $end
$upscope $end
$upscope $end
$enddefinitions $end
$comment Show the parameter values. $end
$dumpall
b11010010 3
$end
#0
$dumpvars
b1 J
b100000000 I
b10000000000000000000000000000011 H
b0 G
bx F
bx E
bx D
b0 C
b0 B
b0 A
bx @
bx ?
bx >
b0 =
b0 <
bx ;
bx :
09
bx 8
b0 7
06
05
14
bx 2
01
00
0/
0.
0-
1,
0+
0*
bx )
0(
0'
bx &
b0 %
bx $
bx #
b0 "
bx !
$end
#2
1.
#4
b0 )
b0 8
b0 2
b0 F
b11111 !
b11111 E
b11111 D
b0 &
b0 ;
b0 :
b1 "
b1 B
b1 A
0.
1/
#6
1.
#8
0.
0/
#10
1.
#12
b10 "
b10 B
b10 A
0.
10
#14
1(
11
b1 G
b10010000 )
b10010000 8
b10010000 2
b10010000 F
1'
19
b1 C
1.
#15
0(
01
b1 &
b1 ;
b1 :
b0 !
b0 E
b0 D
0'
09
#16
b10010000 #
b10010000 ?
0.
00
#18
1(
11
b10 G
b10000001 )
b10000001 8
b10000001 2
b10000001 F
1'
19
b10 C
1.
#19
0(
01
b10 &
b10 ;
b10 :
b1 !
b1 E
b1 D
0'
09
#20
b10000001 #
b10000001 ?
0.
#22
1(
11
b11 G
b1101110 )
b1101110 8
b1101110 2
b1101110 F
1'
19
b11 C
1.
#23
0(
01
b11 &
b11 ;
b11 :
b10 !
b10 E
b10 D
0'
09
#24
b1101110 #
b1101110 ?
0.
#26
1(
11
b100 G
b10010100 )
b10010100 8
b10010100 2
b10010100 F
1'
19
b100 C
1.
#27
0(
01
b100 &
b100 ;
b100 :
b11 !
b11 E
b11 D
0'
09
#28
b10010100 #
b10010100 ?
0.
#30
1(
11
b101 G
b10101011 )
b10101011 8
b10101011 2
b10101011 F
1'
19
b101 C
1.
#31
0(
01
b101 &
b101 ;
b101 :
b100 !
b100 E
b100 D
0'
09
#32
b10101011 #
b10101011 ?
0.
#34
1(
11
b110 G
b1100101 )
b1100101 8
b1100101 2
b1100101 F
1'
19
b110 C
1.
#35
0(
01
b110 &
b110 ;
b110 :
b101 !
b101 E
b101 D
0'
09
#36
b1100101 #
b1100101 ?
0.
#38
1(
11
b111 G
b10001000 )
b10001000 8
b10001000 2
b10001000 F
1'
19
b111 C
1.
#39
0(
01
b111 &
b111 ;
b111 :
b110 !
b110 E
b110 D
0'
09
#40
b10001000 #
b10001000 ?
0.
#42
1(
11
b1000 G
b1001010 )
b1001010 8
b1001010 2
b1001010 F
1'
19
b1000 C
1.
#43
0(
01
b1000 &
b1000 ;
b1000 :
b111 !
b111 E
b111 D
0'
09
#44
b1001010 #
b1001010 ?
0.
#46
1(
11
b1001 G
b1110011 )
b1110011 8
b1110011 2
b1110011 F
1'
19
b1001 C
1.
#47
0(
01
b1001 &
b1001 ;
b1001 :
b1000 !
b1000 E
b1000 D
0'
09
#48
b1110011 #
b1110011 ?
0.
#50
1(
11
b1010 G
b101011 )
b101011 8
b101011 2
b101011 F
1'
19
b1010 C
1.
#51
0(
01
b1010 &
b1010 ;
b1010 :
b1001 !
b1001 E
b1001 D
0'
09
#52
b101011 #
b101011 ?
0.
#54
1(
11
b1011 G
b1010010 )
b1010010 8
b1010010 2
b1010010 F
1'
19
b1011 C
1.
#55
0(
01
b1011 &
b1011 ;
b1011 :
b1010 !
b1010 E
b1010 D
0'
09
#56
b1010010 #
b1010010 ?
0.
#58
1(
11
b1100 G
b111101 )
b111101 8
b111101 2
b111101 F
1'
19
b1100 C
1.
#59
0(
01
b1100 &
b1100 ;
b1100 :
b1011 !
b1011 E
b1011 D
0'
09
#60
b111101 #
b111101 ?
0.
#62
1(
11
b1101 G
b11111 )
b11111 8
b11111 2
b11111 F
1'
19
b1101 C
1.
#63
0(
01
b1101 &
b1101 ;
b1101 :
b1100 !
b1100 E
b1100 D
0'
09
#64
b11111 #
b11111 ?
0.
#66
1(
11
b1110 G
b1110011 )
b1110011 8
b1110011 2
b1110011 F
1'
19
b1110 C
1.
#67
0(
01
b1110 &
b1110 ;
b1110 :
b1101 !
b1101 E
b1101 D
0'
09
#68
b1110011 #
b1110011 ?
0.
#70
1(
11
b1111 G
b1100100 )
b1100100 8
b1100100 2
b1100100 F
1'
19
b1111 C
1.
#71
0(
01
b1111 &
b1111 ;
b1111 :
b1110 !
b1110 E
b1110 D
0'
09
#72
b1100100 #
b1100100 ?
0.
#74
1(
11
b10000 G
b1000111 )
b1000111 8
b1000111 2
b1000111 F
1'
19
b10000 C
1.
#75
0(
01
b10000 &
b10000 ;
b10000 :
b1111 !
b1111 E
b1111 D
0'
09
#76
b1000111 #
b1000111 ?
0.
#78
1(
11
b10001 G
b10110101 )
b10110101 8
b10110101 2
b10110101 F
1'
19
b10001 C
1.
#79
0(
01
b10001 &
b10001 ;
b10001 :
b10000 !
b10000 E
b10000 D
0'
09
#80
b10110101 #
b10110101 ?
0.
#82
1(
11
b10010 G
b11110 )
b11110 8
b11110 2
b11110 F
1'
19
b10010 C
1.
#83
0(
01
b10010 &
b10010 ;
b10010 :
b10001 !
b10001 E
b10001 D
0'
09
#84
b11110 #
b11110 ?
0.
#86
1(
11
b10011 G
b1011111 )
b1011111 8
b1011111 2
b1011111 F
1'
19
b10011 C
1.
#87
0(
01
b10011 &
b10011 ;
b10011 :
b10010 !
b10010 E
b10010 D
0'
09
#88
b1011111 #
b1011111 ?
0.
#90
1(
11
b10100 G
b1000101 )
b1000101 8
b1000101 2
b1000101 F
1'
19
b10100 C
1.
#91
0(
01
b10100 &
b10100 ;
b10100 :
b10011 !
b10011 E
b10011 D
0'
09
#92
b1000101 #
b1000101 ?
0.
#94
1(
11
b10101 G
b1100010 )
b1100010 8
b1100010 2
b1100010 F
1'
19
b10101 C
1.
#95
0(
01
b10101 &
b10101 ;
b10101 :
b10100 !
b10100 E
b10100 D
0'
09
#96
b1100010 #
b1100010 ?
0.
#98
1(
11
b10110 G
b11111 )
b11111 8
b11111 2
b11111 F
1'
19
b10110 C
1.
#99
0(
01
b10110 &
b10110 ;
b10110 :
b10101 !
b10101 E
b10101 D
0'
09
#100
b11111 #
b11111 ?
0.
#102
1(
11
b10111 G
b11000000 )
b11000000 8
b11000000 2
b11000000 F
1'
19
b10111 C
1.
#103
0(
01
b10111 &
b10111 ;
b10111 :
b10110 !
b10110 E
b10110 D
0'
09
#104
b11000000 #
b11000000 ?
0.
#106
1(
11
b11000 G
b10100000 )
b10100000 8
b10100000 2
b10100000 F
1'
19
b11000 C
1.
#107
0(
01
b11000 &
b11000 ;
b11000 :
b10111 !
b10111 E
b10111 D
0'
09
#108
b10100000 #
b10100000 ?
0.
#110
1(
11
b11001 G
b1000101 )
b1000101 8
b1000101 2
b1000101 F
1'
19
b11001 C
1.
#111
0(
01
b11001 &
b11001 ;
b11001 :
b11000 !
b11000 E
b11000 D
0'
09
#112
b1000101 #
b1000101 ?
0.
#114
1(
11
b11010 G
b10010111 )
b10010111 8
b10010111 2
b10010111 F
1'
19
b11010 C
1.
#115
0(
01
b11010 &
b11010 ;
b11010 :
b11001 !
b11001 E
b11001 D
0'
09
#116
b10010111 #
b10010111 ?
0.
#118
1(
11
b11011 G
b10101111 )
b10101111 8
b10101111 2
b10101111 F
1'
19
b11011 C
1.
#119
0(
01
b11011 &
b11011 ;
b11011 :
b11010 !
b11010 E
b11010 D
0'
09
#120
b10101111 #
b10101111 ?
0.
#122
1(
11
b11100 G
b10001101 )
b10001101 8
b10001101 2
b10001101 F
1'
19
b11100 C
1.
#123
0(
01
b11100 &
b11100 ;
b11100 :
b11011 !
b11011 E
b11011 D
0'
09
#124
b10001101 #
b10001101 ?
0.
#126
1(
11
b11101 G
b101000 )
b101000 8
b101000 2
b101000 F
1'
19
b11101 C
1.
#127
0(
01
b11101 &
b11101 ;
b11101 :
b11100 !
b11100 E
b11100 D
0'
09
#128
b101000 #
b101000 ?
0.
#130
1(
11
b11110 G
b10001110 )
b10001110 8
b10001110 2
b10001110 F
1'
19
b11110 C
1.
#131
0(
01
b11110 &
b11110 ;
b11110 :
b11101 !
b11101 E
b11101 D
0'
09
#132
b10001110 #
b10001110 ?
0.
#134
1(
11
b11111 G
b11010 )
b11010 8
b11010 2
b11010 F
1'
19
b11111 C
1.
#135
0(
01
b11111 &
b11111 ;
b11111 :
b11110 !
b11110 E
b11110 D
0'
09
#136
b11010 #
b11010 ?
0.
#138
1(
11
b100000 G
b10111101 )
b10111101 8
b10111101 2
b10111101 F
1'
19
b100000 C
1.
#139
0(
01
b0 &
b0 ;
b0 :
b11111 !
b11111 E
b11111 D
0'
09
#140
b10111101 #
b10111101 ?
b10010000 $
b10010000 >
0.
#142
1(
11
b100001 G
b1101 )
b1101 8
b1101 2
b1101 F
1'
19
b100001 C
1.
#143
0(
01
b1 &
b1 ;
b1 :
b0 !
b0 E
b0 D
0'
09
#144
b1101 #
b1101 ?
b10000001 $
b10000001 >
0.
#146
1(
11
b100010 G
b1011001 )
b1011001 8
b1011001 2
b1011001 F
1'
19
b100010 C
1.
#147
0(
01
b10 &
b10 ;
b10 :
b1 !
b1 E
b1 D
0'
09
#148
b1011001 #
b1011001 ?
b1101110 $
b1101110 >
0.
#150
1(
11
b100011 G
b10100100 )
b10100100 8
b10100100 2
b10100100 F
1'
19
b100011 C
1.
#151
0(
01
b11 &
b11 ;
b11 :
b10 !
b10 E
b10 D
0'
09
#152
b10100100 #
b10100100 ?
b10010100 $
b10010100 >
0.
#154
1(
11
b100100 G
b1001111 )
b1001111 8
b1001111 2
b1001111 F
1'
19
b100100 C
1.
#155
0(
01
b100 &
b100 ;
b100 :
b11 !
b11 E
b11 D
0'
09
#156
b1001111 #
b1001111 ?
b10101011 $
b10101011 >
0.
#158
1(
11
b100101 G
b11000001 )
b11000001 8
b11000001 2
b11000001 F
1'
19
b100101 C
1.
#159
0(
01
b101 &
b101 ;
b101 :
b100 !
b100 E
b100 D
0'
09
#160
b11000001 #
b11000001 ?
b1100101 $
b1100101 >
0.
#162
1(
11
b100110 G
b111000 )
b111000 8
b111000 2
b111000 F
1'
19
b100110 C
1.
#163
0(
01
b110 &
b110 ;
b110 :
b101 !
b101 E
b101 D
0'
09
#164
b111000 #
b111000 ?
b10001000 $
b10001000 >
0.
#166
1(
11
b100111 G
b11000011 )
b11000011 8
b11000011 2
b11000011 F
1'
19
b100111 C
1.
#167
0(
01
b111 &
b111 ;
b111 :
b110 !
b110 E
b110 D
0'
09
#168
b11000011 #
b11000011 ?
b1001010 $
b1001010 >
0.
#170
1(
11
b101000 G
b1011101 )
b1011101 8
b1011101 2
b1011101 F
1'
19
b101000 C
1.
#171
0(
01
b1000 &
b1000 ;
b1000 :
b111 !
b111 E
b111 D
0'
09
#172
b1011101 #
b1011101 ?
b1110011 $
b1110011 >
0.
#174
1(
11
b101001 G
b1011011 )
b1011011 8
b1011011 2
b1011011 F
1'
19
b101001 C
1.
#175
0(
01
b1001 &
b1001 ;
b1001 :
b1000 !
b1000 E
b1000 D
0'
09
#176
b1011011 #
b1011011 ?
b101011 $
b101011 >
0.
#178
1(
11
b101010 G
b111 )
b111 8
b111 2
b111 F
1'
19
b101010 C
1.
#179
0(
01
b1010 &
b1010 ;
b1010 :
b1001 !
b1001 E
b1001 D
0'
09
#180
b111 #
b111 ?
b1010010 $
b1010010 >
0.
#182
1(
11
b101011 G
b10111101 )
b10111101 8
b10111101 2
b10111101 F
1'
19
b101011 C
1.
#183
0(
01
b1011 &
b1011 ;
b1011 :
b1010 !
b1010 E
b1010 D
0'
09
#184
b10111101 #
b10111101 ?
b111101 $
b111101 >
0.
#186
1(
11
b101100 G
b11000001 )
b11000001 8
b11000001 2
b11000001 F
1'
19
b101100 C
1.
#187
0(
01
b1100 &
b1100 ;
b1100 :
b1011 !
b1011 E
b1011 D
0'
09
#188
b11000001 #
b11000001 ?
b11111 $
b11111 >
0.
#190
1(
11
b101101 G
b10111111 )
b10111111 8
b10111111 2
b10111111 F
1'
19
b101101 C
1.
#191
0(
01
b1101 &
b1101 ;
b1101 :
b1100 !
b1100 E
b1100 D
0'
09
#192
b10111111 #
b10111111 ?
b1110011 $
b1110011 >
0.
#194
1(
11
b101110 G
b10010000 )
b10010000 8
b10010000 2
b10010000 F
1'
19
b101110 C
1.
#195
0(
01
b1110 &
b1110 ;
b1110 :
b1101 !
b1101 E
b1101 D
0'
09
#196
b10010000 #
b10010000 ?
b1100100 $
b1100100 >
0.
#198
1(
11
b101111 G
b100101 )
b100101 8
b100101 2
b100101 F
1'
19
b101111 C
1.
#199
0(
01
b1111 &
b1111 ;
b1111 :
b1110 !
b1110 E
b1110 D
0'
09
#200
b100101 #
b100101 ?
b1000111 $
b1000111 >
0.
#202
1(
11
b110000 G
b10110000 )
b10110000 8
b10110000 2
b10110000 F
1'
19
b110000 C
1.
#203
0(
01
b10000 &
b10000 ;
b10000 :
b1111 !
b1111 E
b1111 D
0'
09
#204
b10110000 #
b10110000 ?
b10110101 $
b10110101 >
0.
#206
1(
11
b110001 G
b10111001 )
b10111001 8
b10111001 2
b10111001 F
1'
19
b110001 C
1.
#207
0(
01
b10001 &
b10001 ;
b10001 :
b10000 !
b10000 E
b10000 D
0'
09
#208
b10111001 #
b10111001 ?
b11110 $
b11110 >
0.
#210
1(
11
b110010 G
b111000 )
b111000 8
b111000 2
b111000 F
1'
19
b110010 C
1.
#211
0(
01
b10010 &
b10010 ;
b10010 :
b10001 !
b10001 E
b10001 D
0'
09
#212
b111000 #
b111000 ?
b1011111 $
b1011111 >
0.
#214
1(
11
b110011 G
b101011 )
b101011 8
b101011 2
b101011 F
1'
19
b110011 C
1.
#215
0(
01
b10011 &
b10011 ;
b10011 :
b10010 !
b10010 E
b10010 D
0'
09
#216
b101011 #
b101011 ?
b1000101 $
b1000101 >
0.
#218
1(
11
b110100 G
b1010100 )
b1010100 8
b1010100 2
b1010100 F
1'
19
b110100 C
1.
#219
0(
01
b10100 &
b10100 ;
b10100 :
b10011 !
b10011 E
b10011 D
0'
09
#220
b1010100 #
b1010100 ?
b1100010 $
b1100010 >
0.
#222
1(
11
b110101 G
b1110 )
b1110 8
b1110 2
b1110 F
1'
19
b110101 C
1.
#223
0(
01
b10101 &
b10101 ;
b10101 :
b10100 !
b10100 E
b10100 D
0'
09
#224
b1110 #
b1110 ?
b11111 $
b11111 >
0.
#226
1(
11
b110110 G
b11000101 )
b11000101 8
b11000101 2
b11000101 F
1'
19
b110110 C
1.
#227
0(
01
b10110 &
b10110 ;
b10110 :
b10101 !
b10101 E
b10101 D
0'
09
#228
b11000101 #
b11000101 ?
b11000000 $
b11000000 >
0.
#230
1(
11
b110111 G
b1010000 )
b1010000 8
b1010000 2
b1010000 F
1'
19
b110111 C
1.
#231
0(
01
b10111 &
b10111 ;
b10111 :
b10110 !
b10110 E
b10110 D
0'
09
#232
b1010000 #
b1010000 ?
b10100000 $
b10100000 >
0.
#234
1(
11
b111000 G
b11111 )
b11111 8
b11111 2
b11111 F
1'
19
b111000 C
1.
#235
0(
01
b11000 &
b11000 ;
b11000 :
b10111 !
b10111 E
b10111 D
0'
09
#236
b11111 #
b11111 ?
b1000101 $
b1000101 >
0.
#238
1(
11
b111001 G
b10001110 )
b10001110 8
b10001110 2
b10001110 F
1'
19
b111001 C
1.
#239
0(
01
b11001 &
b11001 ;
b11001 :
b11000 !
b11000 E
b11000 D
0'
09
#240
b10001110 #
b10001110 ?
b10010111 $
b10010111 >
0.
#242
1(
11
b111010 G
b10100110 )
b10100110 8
b10100110 2
b10100110 F
1'
19
b111010 C
1.
#243
0(
01
b11010 &
b11010 ;
b11010 :
b11001 !
b11001 E
b11001 D
0'
09
#244
b10100110 #
b10100110 ?
b10101111 $
b10101111 >
0.
#246
1(
11
b111011 G
b10101011 )
b10101011 8
b10101011 2
b10101011 F
1'
19
b111011 C
1.
#247
0(
01
b11011 &
b11011 ;
b11011 :
b11010 !
b11010 E
b11010 D
0'
09
#248
b10101011 #
b10101011 ?
b10001101 $
b10001101 >
0.
#250
1(
11
b111100 G
b1011100 )
b1011100 8
b1011100 2
b1011100 F
1'
19
b111100 C
1.
#251
0(
01
b11100 &
b11100 ;
b11100 :
b11011 !
b11011 E
b11011 D
0'
09
#252
b1011100 #
b1011100 ?
b101000 $
b101000 >
0.
#254
1(
11
b111101 G
b1010011 )
b1010011 8
b1010011 2
b1010011 F
1'
19
b111101 C
1.
#255
0(
01
b11101 &
b11101 ;
b11101 :
b11100 !
b11100 E
b11100 D
0'
09
#256
b1010011 #
b1010011 ?
b10001110 $
b10001110 >
0.
#258
1(
11
b111110 G
b10101101 )
b10101101 8
b10101101 2
b10101101 F
1'
19
b111110 C
1.
#259
0(
01
b11110 &
b11110 ;
b11110 :
b11101 !
b11101 E
b11101 D
0'
09
#260
b10101101 #
b10101101 ?
b11010 $
b11010 >
0.
#262
1(
11
b111111 G
b1000110 )
b1000110 8
b1000110 2
b1000110 F
1'
19
b111111 C
1.
#263
0(
01
b11111 &
b11111 ;
b11111 :
b11110 !
b11110 E
b11110 D
0'
09
#264
b1000110 #
b1000110 ?
b10111101 $
b10111101 >
0.
#266
1(
11
b1000000 G
b1010100 )
b1010100 8
b1010100 2
b1010100 F
1'
19
b1000000 C
1.
#267
0(
01
b0 &
b0 ;
b0 :
b11111 !
b11111 E
b11111 D
0'
09
#268
b1010100 #
b1010100 ?
b1101 $
b1101 >
0.
#270
1(
11
b1000001 G
b10110 )
b10110 8
b10110 2
b10110 F
1'
19
b1000001 C
1.
#271
0(
01
b1 &
b1 ;
b1 :
b0 !
b0 E
b0 D
0'
09
#272
b10110 #
b10110 ?
b1011001 $
b1011001 >
0.
#274
1(
11
b1000010 G
b101 )
b101 8
b101 2
b101 F
1'
19
b1000010 C
1.
#275
0(
01
b10 &
b10 ;
b10 :
b1 !
b1 E
b1 D
0'
09
#276
b101 #
b101 ?
b10100100 $
b10100100 >
0.
#278
1(
11
b1000011 G
b10111001 )
b10111001 8
b10111001 2
b10111001 F
1'
19
b1000011 C
1.
#279
0(
01
b11 &
b11 ;
b11 :
b10 !
b10 E
b10 D
0'
09
#280
b10111001 #
b10111001 ?
b1001111 $
b1001111 >
0.
#282
1(
11
b1000100 G
b1010 )
b1010 8
b1010 2
b1010 F
1'
19
b1000100 C
1.
#283
0(
01
b100 &
b100 ;
b100 :
b11 !
b11 E
b11 D
0'
09
#284
b1010 #
b1010 ?
b11000001 $
b11000001 >
0.
#286
1(
11
b1000101 G
b10111101 )
b10111101 8
b10111101 2
b10111101 F
1'
19
b1000101 C
1.
#287
0(
01
b101 &
b101 ;
b101 :
b100 !
b100 E
b100 D
0'
09
#288
b10111101 #
b10111101 ?
b111000 $
b111000 >
0.
#290
1(
11
b1000110 G
1'
19
b1000110 C
1.
#291
0(
01
b110 &
b110 ;
b110 :
b101 !
b101 E
b101 D
0'
09
#292
b11000011 $
b11000011 >
0.
#294
1(
11
b1000111 G
b1010000 )
b1010000 8
b1010000 2
b1010000 F
1'
19
b1000111 C
1.
#295
0(
01
b111 &
b111 ;
b111 :
b110 !
b110 E
b110 D
0'
09
#296
b1010000 #
b1010000 ?
b1011101 $
b1011101 >
0.
#298
1(
11
b1001000 G
b0 )
b0 8
b0 2
b0 F
1'
19
b1001000 C
1.
#299
0(
01
b1000 &
b1000 ;
b1000 :
b111 !
b111 E
b111 D
0'
09
