prac5_atempt2/adc.v
// TSC simulation module

// set simulation time:
`timescale 1ns / 1ns

module ADC (
    input wire req,      // Request signal from TSC
    input wire rst,      // Reset signal for ADC
    output reg rdy,      // Ready signal to indicate completion
    output reg [7:0] dat // Data output from the array
);

// Constant array of values (16 data values)
  // reg [7:0]
  // integer adc_data [15:0] = {
  reg [0:7] adc_data [0:15];
    
  initial
    begin 
      // hard-coded ADC values stored in adc_data
      // it seams iVerilog doesn't want to initialize an array
      adc_data[ 0] = 8'h8B;
      adc_data[ 1] = 8'h8C;
      adc_data[ 2] = 8'h99;
      adc_data[ 3] = 8'h9B;
      adc_data[ 4] = 8'h93;
      adc_data[ 5] = 8'h82;
      adc_data[ 6] = 8'h97;
      adc_data[ 7] = 8'h90;
      adc_data[ 8] = 8'h9F;
      adc_data[ 9] = 8'hD7;
      adc_data[10] = 8'h8D;
      adc_data[11] = 8'h9C;
      adc_data[12] = 8'h85;
      adc_data[13] = 8'h8A;
      adc_data[14] = 8'h91;
      adc_data[15] = 8'h8C;
    end
  
  
  reg [7:0] idx = 0; // Index to access the array
  

always @(posedge req or posedge rst) begin
    if (rst) begin
        // Reset the device
        rdy <= 0;
        dat <= 8'b00000000; // Reset data output
        idx <= 0; // Reset array index
    end else if (req) begin
        // Read data from the sample array using modular arithmetic
        dat <= adc_data[idx % 16]; // Wrap around if idx exceeds 15
        idx <= idx + 1;

        // Raise RDY line
        rdy <= 1;
    end else begin
        // Lower RDY line if not processing
        rdy <= 0;
    end
end

endmodule

prac5_atempt2/adc_tb.v
// Test bench simulator for TSC

// set simulation time:
`timescale 1ns / 1ns
`include "adc.v"

module ADC_tb;

  // Parameters
    parameter CLK_PERIOD = 10; // Clock period in ns

    // Signals
    reg req;
    reg rst;
    wire rdy;
    wire [7:0] dat;

    // Instantiate ADC module
    ADC adc_inst (
        .req(req),
        .rst(rst),
        .rdy(rdy),
        .dat(dat)
    );

    // Clock generation
    reg clk = 0;
  
    always #((CLK_PERIOD / 2)) clk = ~clk;

    // Testbench logic
    integer i;
    initial begin
       // rest of your code..
      $dumpfile("wave.vcd");
      $dumpvars(0, ADC_tb);  
        // Reset ADC
      $display("Started ads");
        rst = 1;
        req = 0;
        #10; // Wait for 10 ns
        rst = 0;

        // Wait for a few microseconds
        #100;
      
      // read and display 10 values from ADC to see it is working
      for (i=0; i<10; i++)
        begin
          // Send REQ pulse to ADC to read next value
          req = 1;
          #5; // Pulse width of 5 ns
          req = 0;
          #5
          
          // display the value
          $display("rdy=%b data=%d",rdy,dat);
                    
        end
        
      #20
        
      
        // End simulation
        $finish;
    end

endmodule

prac5_atempt2/wave.vcd
$date
	Sat Apr 27 23:32:26 2024
$end
$version
	Icarus Verilog
$end
$timescale
	1ns
$end
$scope module ADC_tb $end
$var wire 1 ! rdy $end
$var wire 8 " dat [7:0] $end
$var parameter 32 # CLK_PERIOD $end
$var reg 1 $ clk $end
$var reg 1 % req $end
$var reg 1 & rst $end
$var integer 32 ' i [31:0] $end
$scope module adc_inst $end
$var wire 1 % req $end
$var wire 1 & rst $end
$var reg 8 ( dat [7:0] $end
$var reg 8 ) idx [7:0] $end
$var reg 1 ! rdy $end
$upscope $end
$upscope $end
$enddefinitions $end
$comment Show the parameter values. $end
$dumpall
b1010 #
$end
#0
$dumpvars
b0 )
b0 (
bx '
1&
0%
0$
b0 "
0!
$end
#5
1$
#10
0$
0&
#15
1$
#20
0$
#25
1$
#30
0$
#35
1$
#40
0$
#45
1$
#50
0$
#55
1$
#60
0$
#65
1$
#70
0$
#75
1$
#80
0$
#85
1$
#90
0$
#95
1$
#100
0$
#105
1$
#110
1!
b1 )
b10001011 "
b10001011 (
0$
1%
b0 '
#115
1$
0%
#120
b10 )
b10001100 "
b10001100 (
0$
1%
b1 '
#125
1$
0%
#130
b11 )
b10011001 "
b10011001 (
0$
1%
b10 '
#135
1$
0%
#140
b100 )
b10011011 "
b10011011 (
0$
1%
b11 '
#145
1$
0%
#150
b101 )
b10010011 "
b10010011 (
0$
1%
b100 '
#155
1$
0%
#160
b110 )
b10000010 "
b10000010 (
0$
1%
b101 '
#165
1$
0%
#170
b111 )
b10010111 "
b10010111 (
0$
1%
b110 '
#175
1$
0%
#180
b1000 )
b10010000 "
b10010000 (
0$
1%
b111 '
#185
1$
0%
#190
b1001 )
b10011111 "
b10011111 (
0$
1%
b1000 '
#195
1$
0%
#200
b1010 )
b11010111 "
b11010111 (
0$
1%
b1001 '
#205
1$
0%
#210
0$
b1010 '
